[
    {
        "code": "8410891",
        "name": "АМОРТИЗАТОР 80-3401104 привода рул. управления",
        "article": "80-3401104"
    },
    {
        "code": "8463166",
        "name": "АМОРТИЗАТОР ДВИГАТЕЛЯ 240-1001025 ООО \"ТрАз\"",
        "article": "240-1001025"
    },
    {
        "code": "8425666",
        "name": "АМОРТИЗАТОР РАДИАТОРА 70У-1302018 ООО \"ТрАз\"",
        "article": "70У-1302018"
    },
    {
        "code": "8426537",
        "name": "АМОРТИЗАТОР СИДЕНЬЯ (АС20-050-00-000) 80-6809100-11",
        "article": "80-6809100-11"
    },
    {
        "code": "8563531",
        "name": "БАК ГИДРОСИСТЕМЫ ГОРУ 70-3400020-04 с краном (МТЗ-80/82)",
        "article": "70-3400020-04"
    },
    {
        "code": "8406835",
        "name": "БАК ТОПЛИВНЫЙ 70-1101010-02 ПРАВЫЙ ОАО \"МТЗ\"",
        "article": "70-1101010-02"
    },
    {
        "code": "8460301",
        "name": "БАРАБАН 70-1310450",
        "article": "70-1310450"
    },
    {
        "code": "8385699",
        "name": "БЛОК ЦИЛИНДРОВ 240-1002001-Б2 (МТЗ-80/82) ОАО \"ММЗ\"",
        "article": "240-1002001-Б2"
    },
    {
        "code": "8415536",
        "name": "БОЛТ 245-1006020 (распредвала) ОАО \"ММЗ\"",
        "article": "245-1006020"
    },
    {
        "code": "8441993",
        "name": "БОЛТ 245-1008024 ОАО \"ММЗ\"",
        "article": "245-1008024"
    },
    {
        "code": "8425670",
        "name": "БОЛТ 40-4607032 (МТЗ) гидроагрегатов ОАО \"БЗТДиА\"",
        "article": "40-4607032"
    },
    {
        "code": "8452795",
        "name": "БОЛТ 40-4607037 ОАО \"БЗТДиА\"",
        "article": "40-4607037"
    },
    {
        "code": "8475487",
        "name": "БОЛТ 50-1004182-А1 (А20.07.002) (Д-240) шатунный ОАО \"ММЗ\"",
        "article": "50-1004182-А1"
    },
    {
        "code": "8414054",
        "name": "БОЛТ 50-1005127-А (ключ. 19) КРЕПЛЕНИЯ МАХОВИКА К ВАЛУ КОЛЕНЧ. ОАО \"ММЗ\"",
        "article": "50-1005127"
    },
    {
        "code": "8540407",
        "name": "БОЛТ 50-4605019 САЗ",
        "article": "50-1005159"
    },
    {
        "code": "8422660",
        "name": "БОЛТ 50-4605086 СЕРЬГИ БЕЗ ГАЙКИ Аналог",
        "article": "50-4605086"
    },
    {
        "code": "8498328",
        "name": "БОЛТ 50-4605086 СЕРЬГИ С ГАЙКОЙ Аналог 50-4605086 в",
        "article": "сб"
    },
    {
        "code": "8570897",
        "name": "БОЛТ 52-2303026 ДИФФЕРЕНЦИАЛА ПВМ ОАО \"МТЗ\"",
        "article": "52-2303026"
    },
    {
        "code": "8493955",
        "name": "БОЛТ 52-3203026-Б",
        "article": "52-2303026"
    },
    {
        "code": "8463873",
        "name": "БОЛТ 70-1703204 ОАО \"МТЗ\"",
        "article": "70-1703204"
    },
    {
        "code": "8490104",
        "name": "БОЛТ 70-2800016 ОАО \"МТЗ\" (М16х200)",
        "article": "70-2800016"
    },
    {
        "code": "8490587",
        "name": "БОЛТ 70-2800016-01 ОАО \"МТЗ\" (М16Х150)",
        "article": "70-2800016-01"
    },
    {
        "code": "8490085",
        "name": "БОЛТ 70-4216048-Б ОАО \"МТЗ\"",
        "article": "70-4216048-Б"
    },
    {
        "code": "8462035",
        "name": "БОЛТ 72-2203011",
        "article": "72-2203011"
    },
    {
        "code": "8460495",
        "name": "БОЛТ 85-3407105 ОАО \"МТЗ\" НЕ ИСПОЛЬЗОВАТЬ (СМ 8452805)",
        "article": "85-3407105"
    },
    {
        "code": "8433683",
        "name": "БОЛТ ВКЛАДЫША ЗАДНЕЙ СТУПИЦЫ 50-3104028 ОАО \"МТЗ\"",
        "article": "50-3104028"
    },
    {
        "code": "8462543",
        "name": "БОЛТ Д 18.051 САЗ Д",
        "article": "18.051"
    },
    {
        "code": "8461875",
        "name": "БОЛТ ЗАДНЕГО КОЛЕСА 40-3104021 (МТЗ-80) Аналог",
        "article": "40-3104021"
    },
    {
        "code": "8431753",
        "name": "БОЛТ КОЛЕНЧАТОГО ВАЛА 245-1005054-Б ОАО \"ММЗ\"",
        "article": "245-1005054-Б"
    },
    {
        "code": "8487169",
        "name": "БОЛТ КОЛЕНЧАТОГО ВАЛА 245-1005054-В ОАО \"ММЗ\" авто",
        "article": "245-1005054-В"
    },
    {
        "code": "8435998",
        "name": "БОЛТ КРЕПЛЕН. ПЕРЕХОД. К КОЛЛЕКТ. 245-1008023-А ОАО \"ММЗ\"",
        "article": "245-1008023-А"
    },
    {
        "code": "8562147",
        "name": "БОЛТ КРЕПЛЕН. ТУРБОКОМПР. 245-1008031 ОАО \"ММЗ\"",
        "article": "245-1008031"
    },
    {
        "code": "8409533",
        "name": "БОЛТ КРЕПЛЕНИЯ ГБЦ 240-1002047 (МТЗ) длинный ОАО \"ММЗ\"",
        "article": "240-1002047"
    },
    {
        "code": "8498224",
        "name": "БОЛТ КРЕПЛЕНИЯ ГБЦ 240-1002047 (МТЗ) длинный Аналог",
        "article": "240-1002047"
    },
    {
        "code": "8462541",
        "name": "БОЛТ КРЕПЛЕНИЯ ГБЦ 240-1002047-01 (МТЗ) короткий Аналог",
        "article": "240-1002047-01"
    },
    {
        "code": "8409534",
        "name": "БОЛТ КРЕПЛЕНИЯ ГБЦ 240-1002047-01 (МТЗ) короткий ОАО \"ММЗ\"",
        "article": "240-1002047-01"
    },
    {
        "code": "8406580",
        "name": "БОЛТ КРЕПЛЕНИЯ ШКИВА 50-1005054 ОАО \"ММЗ\"",
        "article": "50-1005054"
    },
    {
        "code": "8490106",
        "name": "БОЛТ М12-6Gх.20.88.35.019 ГОСТ 7796-70 (911101) ОАО \"МТЗ\"",
        "article": "911101"
    },
    {
        "code": "8490597",
        "name": "БОЛТ М12-6Gх.35.88.35.019 ГОСТ 7796-70 (911107) ОАО \"МТЗ\"",
        "article": "911107"
    },
    {
        "code": "8461874",
        "name": "БОЛТ ПЕРЕДНЕГО КОЛЕСА 40-3103016 Аналог",
        "article": "40-3103016"
    },
    {
        "code": "8460571",
        "name": "БОЛТ ПОВОРОТНОГО УГОЛЬНИКА Д 18-051 ОАО \"САЗ\" СМ 8462543",
        "article": "Д18-051"
    },
    {
        "code": "8560348",
        "name": "БОЛТ С ГАЙКОЙ (КРЕПЛЕНИЕ КАРДАНА) МТЗ комплект 4 шт РФ",
        "article": "52-2203020"
    },
    {
        "code": "8463167",
        "name": "БОЛТ С ГАЙКОЙ (КРЕПЛЕНИЕ КАРДАНА) МТЗ 52-2203020 Аналог",
        "article": "52-2203020"
    },
    {
        "code": "8459471",
        "name": "БОЛТ СЕРЬГИ 50-4605086 (А61.09.002) ОАО \"МТЗ\"",
        "article": "50-4605086"
    },
    {
        "code": "8489169",
        "name": "БОЛТ ТОРМОЗА 70-3503019 ОАО \"МТЗ\"",
        "article": "70-3503019"
    },
    {
        "code": "8531177",
        "name": "БОЛТ ШТУЦЕРА ТОПЛИВНЫЙ 1 ОТВ 240-1104787 (8мм х1.0х20 обратки) Аналог",
        "article": "240-1104787"
    },
    {
        "code": "8542141",
        "name": "БОЛТ ШТУЦЕРА ТОПЛИВНЫЙ 2 ОТВ 240-1104787 (10мм обратки длинный) Аналог",
        "article": "240-1104787"
    },
    {
        "code": "8484347",
        "name": "БОЛТ ШТУЦЕРА ТОПЛИВНЫЙ 2 ОТВ 240-1104787-Б (8мм обратки)",
        "article": "240-1104787"
    },
    {
        "code": "8386053",
        "name": "БРУС ПЕРЕДНИЙ 70-2801120-А1 (СО ВТУЛКОЙ) (МТЗ-80/82) ОАО \"ВЗТЗЧ\"",
        "article": "70-2801120"
    },
    {
        "code": "8583624",
        "name": "БРЫЗГОВИК ЗАДНИЙ 85-8404041 пластик РФ",
        "article": "85-8404041"
    },
    {
        "code": "8425673",
        "name": "БРЫЗГОВИК ПЕРЕДНИЙ (ШТОРКА) 80-8403030 ООО \"ТрАз\"",
        "article": "80-8403030"
    },
    {
        "code": "8386647",
        "name": "ВАЛ 1 ПЕРЕДАЧИ И ЗАДНЕГО ХОДА 70-1701380 В СБ. ОАО \"МТЗ\"",
        "article": "50-1701380"
    },
    {
        "code": "8460906",
        "name": "ВАЛ ВЕДОМЫЙ ПРИВОДА ВОМ 70-1601021-Б (МТЗ-80) ТАРА",
        "article": "70-1601021"
    },
    {
        "code": "8386176",
        "name": "ВАЛ ВЕДУЩИЙ ПРИВОДА ВОМ 70-1601026 (МТЗ-80/1221) ОАО \"МЗШ\"",
        "article": "70-1601026"
    },
    {
        "code": "8537302",
        "name": "ВАЛ ВЕДУЩИЙ ПРИВОДА ВОМ 70-1601026 (МТЗ-80/1221) МП",
        "article": "70-1601026"
    },
    {
        "code": "8461879",
        "name": "ВАЛ ВЕРТИКАЛЬНЫЙ 52-2308063 (МТЗ-82) Аналог TGT",
        "article": "52-2308063"
    },
    {
        "code": "8386194",
        "name": "ВАЛ ВЕРТИКАЛЬНЫЙ 52-2308063 (МТЗ-82) ОАО \"МТЗ\"",
        "article": "52-2308063"
    },
    {
        "code": "8460903",
        "name": "ВАЛ ВЕРТИКАЛЬНЫЙ 52-2308063 (МТЗ-82) ТАРА",
        "article": "52-2308063"
    },
    {
        "code": "8462546",
        "name": "ВАЛ ВНУТРЕННИЙ ПРОМЕЖУТОЧНОГО ВАЛА 50-1701185 (МТЗ-80) Аналог",
        "article": "50-1701185"
    },
    {
        "code": "8461878",
        "name": "ВАЛ ВТОРИЧНЫЙ 50-1701252 (МТЗ-80) Аналог",
        "article": "50-1701252"
    },
    {
        "code": "8386293",
        "name": "ВАЛ КАРДАННЫЙ 72-2203010-А2 (МТЗ-82) Аналог",
        "article": "72-2203010"
    },
    {
        "code": "8513904",
        "name": "ВАЛ КАРДАННЫЙ 72-2203010-А2 (МТЗ-82) РФ",
        "article": "72-2203010"
    },
    {
        "code": "8538050",
        "name": "ВАЛ КАРДАННЫЙ 72-2203010-А2 (МТЗ-82) РФ **",
        "article": "72-2203010"
    },
    {
        "code": "8386370",
        "name": "ВАЛ КОЛЕНЧАТЫЙ Д-240 243-1005015У БЕЗ ВКЛАДЫШЕЙ ОАО \"ММЗ\"",
        "article": "243-1005015"
    },
    {
        "code": "8461611",
        "name": "ВАЛ КОЛЕНЧАТЫЙ Д-245 245-1005015-А (МТЗ-82.1 - 1025) БЕЗ ВКЛАДЫШЕЙ ОАО \"ММЗ\"",
        "article": "245-1005015"
    },
    {
        "code": "8462550",
        "name": "ВАЛ КРЫШКИ ВОМ 70-4202018 (МТЗ-80) Аналог",
        "article": "70-4202018"
    },
    {
        "code": "8386473",
        "name": "ВАЛ ПЕРВИЧНЫЙ 48-1701032-А ОАО \"МТЗ\"",
        "article": "48-1701032"
    },
    {
        "code": "8460474",
        "name": "ВАЛ ПЕРВИЧНЫЙ 74-1701032 (МТЗ-900/920/950/952) ОАО \"МЗШ\"",
        "article": "74-1701032"
    },
    {
        "code": "8437447",
        "name": "ВАЛ ПЕРВИЧНЫЙ 74-1701032 (МТЗ-952) ОАО \"МЗШ\"",
        "article": "74-1701032"
    },
    {
        "code": "8386484",
        "name": "ВАЛ ПЕРВИЧНЫЙ В СБОРЕ 48-1701030-А ОАО \"МТЗ\"",
        "article": "48-1701030"
    },
    {
        "code": "8386649",
        "name": "ВАЛ ПОВОРОТНЫЙ НАВЕСКИ 70-4605023 ОАО \"САЗ\"",
        "article": "70-4605023"
    },
    {
        "code": "8461882",
        "name": "ВАЛ ПОВОРОТНЫЙ НАВЕСКИ 70-4605023 (МТЗ) Аналог",
        "article": "70-4605023"
    },
    {
        "code": "8462548",
        "name": "ВАЛ ПРОМЕЖУТОЧНЫЙ 70-1701182-Б-02 (МТЗ-80) Аналог",
        "article": "70-1701182Б-02"
    },
    {
        "code": "8386688",
        "name": "ВАЛ ПРОМЕЖУТОЧНЫЙ 70-3401055 (МТЗ-80/1221/1523)*",
        "article": "70-3401055"
    },
    {
        "code": "8489403",
        "name": "ВАЛ ПРОМЕЖУТОЧНЫЙ 50-1701182 (с канавкой) Аналог TGT",
        "article": "50-1701182"
    },
    {
        "code": "8415252",
        "name": "ВАЛ РАСПРЕДЕЛИТЕЛЬНЫЙ 240-1006015 (МТЗ-80) ОАО \"ММЗ\"",
        "article": "240-1006015"
    },
    {
        "code": "8411990",
        "name": "ВАЛ РУЛЕВОГО УПР. 70-3401050-Б (МТЗ) ГОРУ ОАО \"БЗТДиА\"",
        "article": "70-3401050"
    },
    {
        "code": "8425677",
        "name": "ВАЛ РУЛЕВОГО УПР. ГУР 80-3401052-Б ОАО \"ВЗТЗЧ\"",
        "article": "80-3401052"
    },
    {
        "code": "8386565",
        "name": "ВАЛ РУЛЕВОЙ (ГУР) 80-3401072 ОАО \"ВЗТЗЧ\"",
        "article": "80-3401072"
    },
    {
        "code": "8386563",
        "name": "ВАЛ РУЛЕВОЙ 70-3401074-Б ОАО \"БЗТДиА\"",
        "article": "70-3401074"
    },
    {
        "code": "8461881",
        "name": "ВАЛ СИЛОВОЙ 70-1721113 А СТАР. ОБР. (МТЗ-80/82) Аналог",
        "article": "70-1721113А"
    },
    {
        "code": "8526592",
        "name": "ВАЛ СИЛОВОЙ 70-1721113 А СТАР. ОБР. (МТЗ-80/82) \"ТАРА\"",
        "article": "70-1721113А"
    },
    {
        "code": "8438158",
        "name": "ВАЛ СИЛОВОЙ 70-1721113 В НОВ. ОБР. (МТЗ-80/82) ОАО \"БЗТДиА\"",
        "article": "70-1721113В"
    },
    {
        "code": "8386600",
        "name": "ВАЛ ТОРМОЗНОЙ 70-3504055 (МТЗ-80) L-360 мм ОАО \"БЗТДиА\"",
        "article": "70-3504055"
    },
    {
        "code": "8461644",
        "name": "ВАЛ ТОРМОЗНОЙ 70-3504055-01 НОВ. ОБР. (L=380 мм) ОАО \"БЗТДиА\"",
        "article": "70-3504055-01"
    },
    {
        "code": "8466675",
        "name": "ВАЛИК (РПД 1.020) 350-12-095-10-01(ПД) Аналог",
        "article": "350-12-095-10-01"
    },
    {
        "code": "8425679",
        "name": "ВАЛИК (управления ВОМ) 50-4216070-Б ОАО \"МТЗ\"",
        "article": "50-4216070"
    },
    {
        "code": "8411972",
        "name": "ВАЛИК 50-3503015 ОАО \"МТЗ\"",
        "article": "50-3503015"
    },
    {
        "code": "8419063",
        "name": "ВАЛИК 50-4216018",
        "article": "50-4216018"
    },
    {
        "code": "8462552",
        "name": "ВАЛИК 70-1601140 (МТЗ-80) Аналог",
        "article": "70-1601140"
    },
    {
        "code": "8386682",
        "name": "ВАЛИК 70-1601140 (МТЗ-80) ОАО \"ВЗТЗЧ\"",
        "article": "70-1601140"
    },
    {
        "code": "8386666",
        "name": "ВАЛИК ВОДЯНОГО НАСОСА 245-1307052 (Д-243)",
        "article": "245-1307052"
    },
    {
        "code": "8466676",
        "name": "ВАЛИК РУКОЯТИ РПД1003 Аналог",
        "article": "РПД1003"
    },
    {
        "code": "8406594",
        "name": "ВАЛИК УПРАВЛЕНИЯ 50-2401040 ОАО \"МТЗ\"",
        "article": "50-2401040"
    },
    {
        "code": "8406570",
        "name": "ВЕНЕЦ МАХОВИКА ПОД ПУСКАЧ 50Л-1005121 (МТЗ-82) Z=119 ОАО \"ММЗ\"",
        "article": "50Л-1005121"
    },
    {
        "code": "8386739",
        "name": "ВЕНЕЦ МАХОВИКА ПОД СТАРТЕР 50-1005121 (МТЗ-82) Z=145 ОАО \"ММЗ\"",
        "article": "50-1005121"
    },
    {
        "code": "8386793",
        "name": "ВЕНТИЛЯТОР 240-1308040-А (МТЗ-80/82) 4л. МЕТАЛЛ. ОАО \"ММЗ\"",
        "article": "240-1308040А"
    },
    {
        "code": "8446451",
        "name": "ВЕНТИЛЯТОР 245-1308010-А (МТЗ) 6 ЛОПОСТ. ПЛ. Гродно*",
        "article": "245-1308010"
    },
    {
        "code": "8466677",
        "name": "ВЕНТИЛЯТОР 245-1308010-А (МТЗ) МЕТАЛЛ (6 лопастей) Аналог",
        "article": "245-1308010-А"
    },
    {
        "code": "8386911",
        "name": "ВИЛКА 50-1802084 (МТЗ) ОАО \"БЗТДиА\"",
        "article": "50-1802084"
    },
    {
        "code": "8411964",
        "name": "ВИЛКА 50-3401061 ОАО \"ВЗТЗЧ\"",
        "article": "50-3401061"
    },
    {
        "code": "8411966",
        "name": "ВИЛКА 50-3502203 ОАО \"МТЗ\"",
        "article": "50-3502203"
    },
    {
        "code": "8425682",
        "name": "ВИЛКА 74-1702096 (МТЗ-822/950/920/952/900) пер. 2 и 3 передачи ОАО \"МТЗ\"",
        "article": "74-1702096"
    },
    {
        "code": "8462553",
        "name": "ВИЛКА ВКЛ. СЦЕПЛЕНИЯ 50-1601203 (МТЗ) Аналог",
        "article": "50-1601203"
    },
    {
        "code": "8418768",
        "name": "ВИЛКА ПЕРЕКЛЮЧЕНИЯ 1 ПЕРЕДАЧИ И ЗАДНЕГО ХОДА 74-1702086 ОАО \"МТЗ\"",
        "article": "74-1702086"
    },
    {
        "code": "8386909",
        "name": "ВИЛКА ПЕРЕКЛЮЧЕНИЯ 3 ПЕРЕДАЧИ 50-1702096 (МТЗ-80) ОАО \"МТЗ\"",
        "article": "50-1702096"
    },
    {
        "code": "8386910",
        "name": "ВИЛКА ПЕРЕКЛЮЧЕНИЯ 4 И 5 ПЕРЕДАЧ 50-1702116 ОАО \"МТЗ\"",
        "article": "50-1702116"
    },
    {
        "code": "8431783",
        "name": "ВИЛКА ПОПЕРЕЧИНЫ ЗАД. НАВЕСКИ 36-2701036-А3 (БУКСИР А61.11.001) ОАО \"МТЗ\"",
        "article": "36-2701036"
    },
    {
        "code": "8578682",
        "name": "ВИЛКА РАСКОСА 70-4605100 ОАО \"САЗ\"",
        "article": "70-4605100"
    },
    {
        "code": "8425678",
        "name": "ВИНТ 36-1702110 ОАО \"БЗТДиА\"",
        "article": "36-1702110"
    },
    {
        "code": "8442000",
        "name": "ВИНТ 50-1006247 ОАО \"ММЗ\"",
        "article": "50-1006247"
    },
    {
        "code": "8469654",
        "name": "ВИНТ 52-1802093 ОАО \"БЗТДиА\"",
        "article": "52-1802093"
    },
    {
        "code": "8414001",
        "name": "ВИНТ РЕГУЛИРОВОЧНЫЙ 50-1007175-Б1 ОАО \"ММЗ\"",
        "article": "50-1007175-Б1"
    },
    {
        "code": "8425685",
        "name": "ВИНТ СТЯЖКИ А61.04.002-01 левая резьба ОАО \"ВЗТЗЧ\"",
        "article": "А61.04.002-01"
    },
    {
        "code": "8425684",
        "name": "ВИНТ УСТАНОВОЧНЫЙ ВОМ 50-4202068 ОАО \"МТЗ\"",
        "article": "50-4202068"
    },
    {
        "code": "8386927",
        "name": "ВИНТ ЦЕНТРАЛЬНОЙ ТЯГИ С ПАЛЬЦЕМ А61.03.200 ОАО \"САЗ\" (ТОНКИЙ ПАЛЕЦ)",
        "article": "А61.03.200"
    },
    {
        "code": "8474374",
        "name": "ВИНТ ЦЕНТРАЛЬНОЙ ТЯГИ С ПАЛЬЦЕМ А61.03.200-01 (РЗТ)",
        "article": "А61.03.200-01"
    },
    {
        "code": "8387148",
        "name": "ВОДИЛО В СБОРЕ 70-4202060 (МТЗ-80) ОАО \"БЗТДиА\"",
        "article": "70-4202060"
    },
    {
        "code": "8387171",
        "name": "ВОЗДУХООЧИСТИТЕЛЬ 240-1109015А-02 ОАО \"ММЗ\"",
        "article": "240-1109015А-02"
    },
    {
        "code": "8425688",
        "name": "ВТУЛКА 240-1002067-А блока цилиндров ОАО \"ММЗ\"",
        "article": "240-1002067"
    },
    {
        "code": "8425689",
        "name": "ВТУЛКА 240-1002068-А блока цилиндров задняя ОАО \"ММЗ\"",
        "article": "240-1002068"
    },
    {
        "code": "8425690",
        "name": "ВТУЛКА 240-1002069-А блока цилиндров передняя ОАО \"ММЗ\"",
        "article": "240-1002069"
    },
    {
        "code": "8406422",
        "name": "ВТУЛКА 245-1007032-Б-01 направляющая клапана (МТЗ-82) 78мм ОАО \"ММЗ\"",
        "article": "245-1007032-Б-01"
    },
    {
        "code": "8533155",
        "name": "ВТУЛКА 50-1601336",
        "article": "50-1601336"
    },
    {
        "code": "8402328",
        "name": "ВТУЛКА 50-2800011 ОАО \"БЗТДиА\"",
        "article": "50-2800011"
    },
    {
        "code": "8414014",
        "name": "ВТУЛКА 50-4605018-Б ось тяг зад. навески ОАО \"МТЗ\"",
        "article": "50-4605018"
    },
    {
        "code": "8457720",
        "name": "ВТУЛКА 50-4607082-А ОАО \"МТЗ\"",
        "article": "50-4607082"
    },
    {
        "code": "8387429",
        "name": "ВТУЛКА 70-1601053 ОАО \"БЗТДиА\"",
        "article": "70-1601053"
    },
    {
        "code": "8425693",
        "name": "ВТУЛКА 70-1601074 диск средний ОАО \"САЗ\"",
        "article": "70-1601074"
    },
    {
        "code": "8406855",
        "name": "ВТУЛКА 70-1701225 (МТЗ)",
        "article": "70-1701225"
    },
    {
        "code": "8463877",
        "name": "ВТУЛКА 70-1703013 ОАО \"МТЗ\"",
        "article": "70-1703013"
    },
    {
        "code": "8457529",
        "name": "ВТУЛКА 70-2409027-А ООО \"ТрАз\"",
        "article": "70-2409027"
    },
    {
        "code": "8387432",
        "name": "ВТУЛКА 70-4605032 вал поворот. зад. навески ОАО \"САЗ\"",
        "article": "70-4605032"
    },
    {
        "code": "8422878",
        "name": "ВТУЛКА 70-4605047-01 (МТЗ) ограничительная тяги центральной зад. навески ОАО \"БЗТДиА\"",
        "article": "70-4605047"
    },
    {
        "code": "8436211",
        "name": "ВТУЛКА 72-1802062 А1 ОАО \"БЗТДиА\"",
        "article": "72-1802062"
    },
    {
        "code": "8387433",
        "name": "ВТУЛКА 72-2209017 ОАО \"БЗТДиА\"",
        "article": "72-2209017"
    },
    {
        "code": "8444606",
        "name": "ВТУЛКА 74-1721028 ОАО \"МТЗ\"",
        "article": "74-1721028"
    },
    {
        "code": "8471043",
        "name": "ВТУЛКА БРУСА 40-3001022 (МТЗ-80/82/1221) Аналог",
        "article": "40-3001022"
    },
    {
        "code": "8387276",
        "name": "ВТУЛКА БРУСА 40-3001022 (МТЗ-80/82/1221) ОАО \"ВЗТЗЧ\"",
        "article": "40-3001022"
    },
    {
        "code": "8490078",
        "name": "ВТУЛКА ОСИ ТЯГ НИЖ 70-4605047 ОАО \"МТЗ\"",
        "article": "70-4605047"
    },
    {
        "code": "8422689",
        "name": "ВТУЛКА ПРОМОПОРЫ 50-1701188 ОАО \"МТЗ\"",
        "article": "50-1701188"
    },
    {
        "code": "8387438",
        "name": "ВТУЛКА РЕГУЛИРОВОЧНАЯ 50-3405026 (МТЗ) ОАО \"БЗТДиА\"",
        "article": "50-3405026"
    },
    {
        "code": "8387337",
        "name": "ВТУЛКА РУЛЕВАЯ 80-3401070 (МТЗ-80/82) ОАО \"ВЗТЗЧ\"",
        "article": "80-3401070"
    },
    {
        "code": "8411002",
        "name": "ВТУЛКА СФЕРИЧЕСКАЯ Ф80-3405107 гидроцилиндра рул.упр-ния",
        "article": "80-3405107"
    },
    {
        "code": "8462558",
        "name": "ВТУЛКА ЦАПФЫ 50-3001021 НИЖНЯЯ Аналог",
        "article": "50-3001021"
    },
    {
        "code": "8436213",
        "name": "ВТУЛКА ЦАПФЫ 70-3001062 (МТЗ-82) ОАО \"БЗТДиА\"",
        "article": "70-3001062"
    },
    {
        "code": "8436212",
        "name": "ВТУЛКА ЦАПФЫ 80-3001068 А (МТЗ-82) ОАО \"БЗТДиА\"",
        "article": "80-3001068"
    },
    {
        "code": "8413930",
        "name": "ВТУЛКА ШАТУНА 240-1004115 (под 38 палец) ОАО \"ММЗ\"",
        "article": "240-1004115"
    },
    {
        "code": "8482325",
        "name": "ВТУЛКА ШАТУНА 245-1004115-А (под 42 палец) ОАО \"ММЗ\"",
        "article": "245-1004115"
    },
    {
        "code": "8411475",
        "name": "ГАЙКА 50-1003104 колпака крышки ГБЦ ОАО \"ММЗ\"",
        "article": "50-1003104"
    },
    {
        "code": "8475489",
        "name": "ГАЙКА 50-1004188 (А20.03.001) (Д-240) БОЛТА ШАТУН. ОАО \"ММЗ\"",
        "article": "50-1004188"
    },
    {
        "code": "8387688",
        "name": "ГАЙКА 50-3405052 ОАО \"БЗТДиА\"",
        "article": "50-3405052"
    },
    {
        "code": "8387689",
        "name": "ГАЙКА 50-3405053 ОАО \"БЗТДиА\"",
        "article": "50-3405053"
    },
    {
        "code": "8414017",
        "name": "ГАЙКА 52-2308097 полуоси, вала вертикального ОАО \"САЗ\"",
        "article": "52-2308097"
    },
    {
        "code": "8489170",
        "name": "ГАЙКА 70-3401078 ОАО \"БЗТДиА\"",
        "article": "70-3401078"
    },
    {
        "code": "8414028",
        "name": "ГАЙКА 70-4202083-А ОАО \"САЗ\"",
        "article": "70-4202083"
    },
    {
        "code": "8461889",
        "name": "ГАЙКА А04.02.020-01 нижней оси навески Аналог",
        "article": "А04.02.020-01"
    },
    {
        "code": "8462560",
        "name": "ГАЙКА ВТОРИЧНОГО ВАЛА 50-1701253 Аналог",
        "article": "50-1701253"
    },
    {
        "code": "8387605",
        "name": "ГАЙКА ВТОРИЧНОГО ВАЛА 50-1701253-01 (МТЗ-80) ОАО \"БЗТДиА\"",
        "article": "50-1701253"
    },
    {
        "code": "8457884",
        "name": "ГАЙКА ДИФФЕРЕНЦИАЛА ПВМ 52-2302038",
        "article": "52-2302038"
    },
    {
        "code": "8461887",
        "name": "ГАЙКА ЗАДНЕГО КОЛЕСА 36-3104019 Аналог",
        "article": "36-3104019"
    },
    {
        "code": "8431779",
        "name": "ГАЙКА М12*1,25 6Н.6.019 ГОСТ 5916-70 ОАО \"БЗТДиА\" М12*1,25",
        "article": "6Н.6.019"
    },
    {
        "code": "8435793",
        "name": "ГАЙКА М16-6Н.6.019 913059 ОАО \"МТЗ\"",
        "article": "913059"
    },
    {
        "code": "8435795",
        "name": "ГАЙКА М20-6Н.6.019 913073 ОАО \"МТЗ\"",
        "article": "913073"
    },
    {
        "code": "8525930",
        "name": "ГАЙКА М20х1,5-6Н.6.019 913077 (КОРОНЧАТАЯ) ГОСТ 5919-73 ОАО \"МТЗ\"",
        "article": "913077"
    },
    {
        "code": "8414026",
        "name": "ГАЙКА НИЖНЯЯ 70-3003032 ОАО \"САЗ\"",
        "article": "70-3003032"
    },
    {
        "code": "8462559",
        "name": "ГАЙКА ПРОМЕЖУТОЧНОГО ВАЛА 50-1701181 (МТЗ-80) Аналог",
        "article": "50-1701181"
    },
    {
        "code": "8387660",
        "name": "ГАЙКА ПРОМЕЖУТОЧНОГО ВАЛА 50-1701181 (МТЗ-80) ОАО \"БЗТДиА\"",
        "article": "50-1701181"
    },
    {
        "code": "8406546",
        "name": "ГАЙКА СТУПИЦЫ ПЕРЕДНЕГО КОЛЕСА 40-3103017 ОАО \"САЗ\"",
        "article": "40-3103017"
    },
    {
        "code": "8461888",
        "name": "ГАЙКА СТУПИЦЫ ПЕРЕДНЕГО КОЛЕСА 40-3103017 (МТЗ) Аналог",
        "article": "40-3103017"
    },
    {
        "code": "8461890",
        "name": "ГИЛЬЗА ШКВОРНЯ 52-2308084 А1 Аналог",
        "article": "52-2308084"
    },
    {
        "code": "8387903",
        "name": "ГИЛЬЗА ШКВОРНЯ 52-2308084-А1 ОАО \"МТЗ\"",
        "article": "52-2308084"
    },
    {
        "code": "8445887",
        "name": "ГЛУШИТЕЛЬ ДЛИННЫЙ 60-1205015А2 (МТЗ-80) Аналог",
        "article": "60-1205015А2"
    },
    {
        "code": "8387979",
        "name": "ГЛУШИТЕЛЬ ДЛИННЫЙ 60-1205015А2 (МТЗ-80) НОВОСАД.",
        "article": "60-1205015А2"
    },
    {
        "code": "8541004",
        "name": "ГЛУШИТЕЛЬ КОРОТКИЙ 60-1205015 термоэмаль",
        "article": "60-1205015"
    },
    {
        "code": "8445888",
        "name": "ГЛУШИТЕЛЬ КОРОТКИЙ 60-1205015А (МТЗ-80; Т-40) Аналог",
        "article": "60-1205015А"
    },
    {
        "code": "8425698",
        "name": "ГНЕЗДО 50-1701191 ОАО \"МТЗ\"",
        "article": "50-1701191"
    },
    {
        "code": "8387989",
        "name": "ГНЕЗДО ВНУТРЕННЕГО ВАЛА ПЕРЕДНЕЕ (МТЗ-80) 70-1701186 ООО \"САЛЕО\"",
        "article": "70-1701186"
    },
    {
        "code": "8460911",
        "name": "ГНЕЗДО ВНУТРЕННЕГО ВАЛА ПЕРЕДНЕЕ (МТЗ-80) 70-1701186 ТАРА",
        "article": "70-1701186"
    },
    {
        "code": "8388009",
        "name": "ГОЛОВКА БЛОКА ЦИЛИНДРОВ Д-240 240-1003012-А1 ОАО \"ММЗ\"",
        "article": "240-1003012А1"
    },
    {
        "code": "8476510",
        "name": "ГОЛОВКА БЛОКА ЦИЛИНДРОВ Д-243 240-1003012-Б1 под свечи накал ОАО \"ММЗ\"",
        "article": "240-1003012Б1"
    },
    {
        "code": "8388494",
        "name": "ДЕРЖАТЕЛЬ 70-6804011 (МТЗ-80) ОАО \"БЗТДиА\"",
        "article": "70-6804011"
    },
    {
        "code": "8406861",
        "name": "ДИАФРАГМА 70-2409021 блокировки дифференциала (МТЗ-80/1221/1523) ООО \"ТрАз\"",
        "article": "70-2409021"
    },
    {
        "code": "8388699",
        "name": "ДИСК ведущий дифференциала 52-2303023 А1 (МТЗ-80/1221/1523) ОАО \"МТЗ\"",
        "article": "52-2303023"
    },
    {
        "code": "8388538",
        "name": "ДИСК ЗАДНЕГО КОЛЕСА DW14L-38 С70-3107020 (МТЗ-80/82/822/1021) ОАО \"БЗТДиА\"",
        "article": "С70-3107020"
    },
    {
        "code": "8388664",
        "name": "ДИСК НАЖИМНОЙ 70-1601093 (МТЗ) ОАО \"БЗТДиА\"",
        "article": "70-1601093"
    },
    {
        "code": "8388717",
        "name": "ДИСК НАЖИМНОЙ 80-1601093 (МТЗ-82) ОАО \"БЗТДиА\"",
        "article": "80-1601093"
    },
    {
        "code": "8462900",
        "name": "ДИСК ПЕРЕДНЕГО КОЛЕСА 7Х20 775-3101012-04 (ЛТЗ,Т-40, МТЗ-82 УЗКИЙ СБОРНЫЙ 5 ОТВ.) КРЕМЕНЧУГ",
        "article": "775-3101012-04"
    },
    {
        "code": "8418678",
        "name": "ДИСК ПЕРЕДНЕГО КОЛЕСА 9х20 3101020-А-02, 8 шпил. (МТЗ-82), под шину 11,2-R20 ОАО \"БЗТДиА\"",
        "article": "3101020-А-02"
    },
    {
        "code": "8388593",
        "name": "ДИСК ПЕРЕДНЕГО КОЛЕСА УЗКИЙ 5,5х20 40-3101010А3 (МТЗ-80) ОАО \"БЗТДиА\"",
        "article": "40-3101010А3"
    },
    {
        "code": "8405397",
        "name": "ДИСК промежуточной опоры (025) 72-2209026 (МТЗ) (звездочка) ОАО \"БЗТДиА\"",
        "article": "72-2209026"
    },
    {
        "code": "8406881",
        "name": "ДИСК промежуточной опоры ведущий 72-2209027 (МТЗ) (тонкий) ОАО \"БЗТДиА\"",
        "article": "72-2209027"
    },
    {
        "code": "8406879",
        "name": "ДИСК промежуточной опоры нажимной 72-2209019 (МТЗ) (толстый) ОАО \"БЗТДиА\"",
        "article": "72-2209019"
    },
    {
        "code": "8462562",
        "name": "ДИСК СЦЕПЛЕНИЯ ВЕДОМЫЙ 70-1601130 (МТЗ) пружина Аналог",
        "article": "70-1601130"
    },
    {
        "code": "8435442",
        "name": "ДИСК СЦЕПЛЕНИЯ ВЕДОМЫЙ 80-1601130-А (МТЗ-80/82) Д-243 Диск с сегмент. 12 шл. БЗТДиА *",
        "article": "80-1601130-А"
    },
    {
        "code": "8406970",
        "name": "ДИСК СЦЕПЛЕНИЯ ВЕДОМЫЙ 85-1601130 (Д-243,Д-245) резин ОАО \"БЗТДиА\"",
        "article": "85-1601130"
    },
    {
        "code": "8556602",
        "name": "ДИСК СЦЕПЛЕНИЯ ВЕДОМЫЙ 85-1601130-Д-01 ОАО \"БЗТДиА\"",
        "article": "85-1601130Д-01"
    },
    {
        "code": "8388678",
        "name": "ДИСК ТОРМОЗНОЙ НАЖИМНОЙ (СТАЛЬН) 50-3502030 А (МТЗ-80/82) ОАО \"ВЗТЗЧ\"",
        "article": "50-3502030"
    },
    {
        "code": "8461892",
        "name": "ДИСК ТОРМОЗНОЙ С НАКЛАД. 50-3502040А (D=175 мм) (МТЗ-80) Аналог",
        "article": "50-3502040"
    },
    {
        "code": "8388677",
        "name": "ДИСК ТОРМОЗНОЙ С НАКЛАД. 70-3502040-01 (D=180 мм.) (МТЗ-80/82) ОАО \"БЗТДиА\"",
        "article": "70-3502040"
    },
    {
        "code": "8448959",
        "name": "ДИСК ТОРМОЗНОЙ С НАКЛАД. 70-3502040-08 (D=180 мм.) (МТЗ-80/82) ТИИР",
        "article": "70-3502040"
    },
    {
        "code": "8441488",
        "name": "ЗАГЛУШКА 240-1003027-А2 ОАО \"ММЗ\"",
        "article": "240-1003027"
    },
    {
        "code": "8441998",
        "name": "ЗАГЛУШКА 240-1003037 ОАО \"ММЗ\"",
        "article": "240-1003037"
    },
    {
        "code": "8486585",
        "name": "ЗАГЛУШКА 45-08КП.Ц9.ХР ОАО \"ММЗ\"",
        "article": "45-08КП.Ц9.ХР"
    },
    {
        "code": "8482158",
        "name": "ЗАГЛУШКА 52-2301067 ОАО \"МТЗ\"",
        "article": "52-2301067"
    },
    {
        "code": "8544042",
        "name": "ЗАГЛУШКА 82-2302031",
        "article": "82-2302031"
    },
    {
        "code": "8412047",
        "name": "ЗАКРЫЛОК ЛЕВЫЙ 80-8404020-Б ОАО \"МТЗ\"",
        "article": "80-8404020-Б"
    },
    {
        "code": "8412048",
        "name": "ЗАКРЫЛОК ПРАВЫЙ 80-8404020-Б-01 ОАО \"МТЗ\"",
        "article": "80-8404020-Б-01"
    },
    {
        "code": "8432080",
        "name": "ЗАМОК ДВЕРИ ПРАВЫЙ УК 80-6105010-01 В СБ. ОАО \"МТЗ\"",
        "article": "80-6105010-01"
    },
    {
        "code": "8482661",
        "name": "ЗАМОК ДВЕРНОЙ ЛЕВЫЙ УК 80-6105010 в СБ Аналог",
        "article": "80-6105010"
    },
    {
        "code": "8414037",
        "name": "ЗАМОК ДВЕРНОЙ ЛЕВЫЙ УК 80-6105050 ОАО \"МТЗ\"",
        "article": "80-6105050"
    },
    {
        "code": "8389124",
        "name": "ЗАМОК ДВЕРНОЙ ПРАВЫЙ УК 80-6105050-01 ОАО \"МТЗ\"",
        "article": "80-6105050-01"
    },
    {
        "code": "8488168",
        "name": "ЗАМОК КРЫШИ 80-6707070 ОАО \"МТЗ\"",
        "article": "80-6707070"
    },
    {
        "code": "8414040",
        "name": "ЗАМОК НА КАПОТ 80-8402410 ОАО \"МТЗ\"",
        "article": "80-8402410"
    },
    {
        "code": "8488167",
        "name": "ЗАЩЕЛКА А37.09.010 (крыши) ОАО \"МТЗ\"",
        "article": "А37.09.010"
    },
    {
        "code": "8414039",
        "name": "ЗЕРКАЛО 80-8201050 (пластик,наружнее,УК) 165х315 Аналог",
        "article": "80-8201050"
    },
    {
        "code": "8463515",
        "name": "ЗЕРКАЛО ВНУТРИСАЛОН 80-8201030",
        "article": "80-8201030"
    },
    {
        "code": "8389828",
        "name": "КАРДАН РУЛЕВОЙ 50-3401060 (МТЗ-80) ОАО \"ВЗТЗЧ\"",
        "article": "50-3401060"
    },
    {
        "code": "8456952",
        "name": "КЛАПАН ВПУСКНОЙ 240-1007014-Б9 (Луганск)",
        "article": "240-1007014Б9"
    },
    {
        "code": "8453401",
        "name": "КЛАПАН ВЫПУСКНОЙ 240-1007015-Б9 (Луганск)",
        "article": "240-1007015"
    },
    {
        "code": "8406611",
        "name": "КЛИН 52-2301056 ОАО \"МТЗ\"",
        "article": "52-2301056"
    },
    {
        "code": "8532563",
        "name": "КЛИН 52-2301056-01 РФ",
        "article": "52-2301056-01"
    },
    {
        "code": "8540924",
        "name": "КОВРИК КАБИНЫ УК 80-6702337 А (МТЗ-80-1221) (БЕЛ) ООО \"ТрАз\"",
        "article": "80-6702337"
    },
    {
        "code": "8571174",
        "name": "КОВРИК КАБИНЫ УК 80-6702340-В (МТЗ-80-1221) (с вырезом под рычаг КПП и ручник) ООО \"ТрАз\"",
        "article": "80-6702340-В"
    },
    {
        "code": "8390525",
        "name": "КОЖУХ РАБОЧЕГО ТОРМОЗА 70-3502035 ОАО \"МТЗ\"",
        "article": "70-3502035"
    },
    {
        "code": "8462569",
        "name": "КОЖУХ РАБОЧЕГО ТОРМОЗА 70-3502035 (МТЗ) Аналог",
        "article": "70-3502035"
    },
    {
        "code": "8465356",
        "name": "КОЖУХ РАДИАТОРА 70-1309080 (ДИФФУЗОР) Аналог",
        "article": "70-1309080"
    },
    {
        "code": "8417400",
        "name": "КОЖУХ СТОЯНОЧНОГО ТОРМОЗА 50-3502035-А2 ОАО \"МТЗ\"",
        "article": "50-3502035"
    },
    {
        "code": "8390646",
        "name": "КОЛЛЕКТОР ВЫПУСКНОЙ 240-1008015 А1 С ПАТРУБ. ОАО \"ММЗ\"",
        "article": "240-1008015"
    },
    {
        "code": "8406433",
        "name": "КОЛЛЕКТОР ВЫПУСКНОЙ 240-1008025 (БЕЗ ПАТР) ОАО \"ММЗ\"",
        "article": "240-1008025"
    },
    {
        "code": "8441136",
        "name": "КОЛЛЕКТОР ВЫПУСКНОЙ 245-1008025 (Д-245.5) (МТЗ-892) ОАО \"ММЗ\"",
        "article": "245-1008025"
    },
    {
        "code": "8483923",
        "name": "КОЛЬЦО 17-4 ПОД ГАЙКУ КОЛПАКА 50-1003107-А (круглое) ООО \"ТрАз\"",
        "article": "50-1003107"
    },
    {
        "code": "8531124",
        "name": "КОЛЬЦО 22-4 ПОД ГАЙКУ КОЛПАКА 50-1003107-01А (конусное) ООО \"ТрАз\"",
        "article": "50-1003107-01"
    },
    {
        "code": "8482157",
        "name": "КОЛЬЦО 52-1802102-А ОАО \"МТЗ\"",
        "article": "52-1802102"
    },
    {
        "code": "8411978",
        "name": "КОЛЬЦО 52-2302018 ОАО \"МТЗ\"",
        "article": "52-2302018"
    },
    {
        "code": "8422875",
        "name": "КОЛЬЦО 85-2407043",
        "article": "85-2407043"
    },
    {
        "code": "8460531",
        "name": "КОЛЬЦО МАСЛООТРАЖАТЕЛЬНОЕ 240-1002311",
        "article": "240-1002311"
    },
    {
        "code": "8423908",
        "name": "КОЛЬЦО РЕЗИНОВОЕ 52-2308091А (МТЗ-82 трубы шкворня) ООО \"ТрАз\"",
        "article": "52-2308091"
    },
    {
        "code": "8441978",
        "name": "КОЛЬЦО СТОПОРНОЕ ПОРШНЕВОГО ПАЛЬЦА 240-1004022 ОАО \"ММЗ\"",
        "article": "240-1004022"
    },
    {
        "code": "8520035",
        "name": "КОМПЛЕКТ ПЕРЕОБОРУДОВАНИЯ ГУР В ГОРУ (МТЗ-82) (БЕЗ",
        "article": "БАЧКА)"
    },
    {
        "code": "8531127",
        "name": "КОМПЛЕКТ ПЕРЕОБОРУДОВАНИЯ С ПД ПОД СТАРТЕР (ПЛИТА С МЕТИЗАМИ) без разборки",
        "article": "двигателя"
    },
    {
        "code": "8536513",
        "name": "КОМПЛЕКТ ПОД НАСОС ДОЗАТОР (плита + болты) ООО",
        "article": "\"ТРаЗ\""
    },
    {
        "code": "8582613",
        "name": "КОМПЛЕКТ УСИЛЕННЫХ НАКОНЕЧНИКОВ ТЯГИ РУЛЕВОЙ 80-3003020-02/03 РФ",
        "article": "80-3003020-02/03"
    },
    {
        "code": "8512903",
        "name": "КОМПЛЕКТ ЧЕХЛОВ (80В-6804500-А,",
        "article": "80В-6805500-А)"
    },
    {
        "code": "8403415",
        "name": "КОМПЛЕКТ ШЕСТЕРЕН 50-2403014 (МТЗ-80) ГЛ.ПАРА",
        "article": "50-2403014"
    },
    {
        "code": "8499897",
        "name": "КОМПЛЕКТ шестерен гл. передачи 52-2302010-Р с корпусом хвост. Аналог",
        "article": "52-2302010"
    },
    {
        "code": "8411977",
        "name": "КОМПЛЕКТ шестерен гл. передачи 52-2302010-Р с корпусом хвост. ОАО \"МТЗ\"",
        "article": "52-2302010-Р"
    },
    {
        "code": "8388688",
        "name": "КОРЗИНА 245-1601090 (МТЗ)*",
        "article": "245-1601090"
    },
    {
        "code": "8391195",
        "name": "КОРЗИНА СЦЕПЛЕНИЯ 70-1601090-А Д-240 ОАО \"БЗТДиА\" ст.обр.",
        "article": "70-1601090"
    },
    {
        "code": "8391178",
        "name": "КОРЗИНА СЦЕПЛЕНИЯ 80-1601090 ОАО \"БЗТДиА\"",
        "article": "80-1601090"
    },
    {
        "code": "8569109",
        "name": "КОРЗИНА СЦЕПЛЕНИЯ 80-1601090 Аналог",
        "article": "80-1601090"
    },
    {
        "code": "8388698",
        "name": "КОРЗИНА СЦЕПЛЕНИЯ 85-1601090-Д-01 (ЛЕПЕСТКОВАЯ УСИЛЕННАЯ) ОАО \"БЗТДиА\"",
        "article": "80-1601090-Д-01"
    },
    {
        "code": "8462570",
        "name": "КОРОМЫСЛО 50-1007212 (МТЗ) Аналог",
        "article": "50-1007212"
    },
    {
        "code": "8391393",
        "name": "КОРПУС 52-1802073 ОАО \"БЗТДиА\"",
        "article": "52-1802073"
    },
    {
        "code": "8453450",
        "name": "КОРПУС ВИЛОК 50-1702080 Аналог",
        "article": "50-1702080"
    },
    {
        "code": "8391321",
        "name": "КОРПУС ВИЛОК 50-1702080-А (МТЗ-80/82) ОАО \"МТЗ\"",
        "article": "50-1702080"
    },
    {
        "code": "8425701",
        "name": "КОРПУС САЛЬНИКА 240-1002300 ОАО \"ММЗ\"",
        "article": "240-1002300"
    },
    {
        "code": "8480123",
        "name": "КОРПУС САПУНА 240-1002430-Г ОАО \"ММЗ\"",
        "article": "240-1002430"
    },
    {
        "code": "8434718",
        "name": "КОРПУС ТОПЛ. ФИЛЬТРА 245-1117075 (Д-243; Д-245) со штуцером ОАО \"ММЗ\"",
        "article": "245-1117075"
    },
    {
        "code": "8417969",
        "name": "КОРПУС ТОПЛИВНОГО ФИЛЬТРА 240-1117025-А1 ОАО \"ММЗ\"",
        "article": "240-1117025"
    },
    {
        "code": "8462207",
        "name": "КОРПУС ТОПЛИВНОГО ФИЛЬТРА ТОНКОЙ ОЧИСТКИ МТЗ 245-1117010-Г ОАО \"ММЗ\"",
        "article": "245-1117010-Г"
    },
    {
        "code": "8462571",
        "name": "КОРПУС УПЛОТНЕНИЯ 52-2308101 (МТЗ) Аналог",
        "article": "52-2308101"
    },
    {
        "code": "8461950",
        "name": "КРАН ОТОПИТЕЛЯ СЛИВНОЙ КР 29 (ВС-11) Аналог КР 29",
        "article": "(ВС-11)"
    },
    {
        "code": "8391509",
        "name": "КРАН ОТОПИТЕЛЯ СЛИВНОЙ КР 29 (ВС-11) ООО \"Старт\" КР 29",
        "article": "(ВС-11)"
    },
    {
        "code": "8462641",
        "name": "КРАН СЛИВНОЙ БЛОКА ЦИЛИНДРОВ,РАДИАТОРА КР2/ПС7 Аналог",
        "article": "КР2/ПС7"
    },
    {
        "code": "8392159",
        "name": "КРАН СЛИВНОЙ БЛОКА ЦИЛИНДРОВ,РАДИАТОРА ПС7-0/КР2 ООО \"Старт\"",
        "article": "ПС7-0/КР2"
    },
    {
        "code": "8391563",
        "name": "КРАН ТОПЛИВНОГО БАКА КР25/ПП6-1 (МТЗ-80) Аналог",
        "article": "КР25/ПП6-1"
    },
    {
        "code": "8465359",
        "name": "КРАН ТОПЛИВНОГО БАКА КР25/ПП6-1-0 (МТЗ-80/82) ООО \"Старт\"",
        "article": "КР25/ПП6-1"
    },
    {
        "code": "8461951",
        "name": "КРАН ТОПЛИВНОГО БАКА ПД (ПП3) КР-12Д Аналог",
        "article": "КР-12Д"
    },
    {
        "code": "8391741",
        "name": "КРЕСТОВИНА ДИФФЕРЕНЦИАЛА 50-2403062- А2 ОАО \"МТЗ\"",
        "article": "50-2403062"
    },
    {
        "code": "8554570",
        "name": "КРЕСТОВИНА КАРДАННОГО ВАЛА 72-2203025 (82/1221/1523) РФ+",
        "article": "72-2203025"
    },
    {
        "code": "8461952",
        "name": "КРЕСТОВИНА КАРДАННОГО ВАЛА 72-2203025 (МТЗ-82/1221/1523) Аналог",
        "article": "72-2203025"
    },
    {
        "code": "8513905",
        "name": "КРЕСТОВИНА КАРДАННОГО ВАЛА 72-2203025 (МТЗ-82/1221/1523) РФ",
        "article": "72-2203025"
    },
    {
        "code": "8391727",
        "name": "КРЕСТОВИНА РУЛЕВОГО КАРДАНЧИКА 50-3401062 ОАО \"ВЗТЗЧ\"",
        "article": "50-3401062"
    },
    {
        "code": "8411973",
        "name": "КРОНШТЕЙН 50-4202058 ОАО \"БЗТДиА\"",
        "article": "50-4202058"
    },
    {
        "code": "8457723",
        "name": "КРОНШТЕЙН 80-4803151 ОАО \"МТЗ\"",
        "article": "80-4803151"
    },
    {
        "code": "8489679",
        "name": "КРОНШТЕЙН ГЕНЕРАТОРА 240-3701056-В (МТЗ-80/82) ОАО \"ММЗ\"",
        "article": "240-3701056-В"
    },
    {
        "code": "8391821",
        "name": "КРОНШТЕЙН КАБИНЫ 80-6702068 ЛЕВЫЙ (2 РЕЗЬБ. ОТВ.) (МТЗ-80) ОАО \"ВЗТЗЧ\"",
        "article": "80-6702068"
    },
    {
        "code": "8419666",
        "name": "КРОНШТЕЙН КАБИНЫ 80-6702069 ПРАВЫЙ (МТЗ-80) ОАО \"ВЗТЗЧ\"",
        "article": "80-6702069"
    },
    {
        "code": "8417035",
        "name": "КРОНШТЕЙН КРЫЛА 72-8403016 (МК)",
        "article": "72-8403016"
    },
    {
        "code": "8417034",
        "name": "КРОНШТЕЙН КРЫЛА 80-8403021-01 (УК)",
        "article": "80-8403021-01"
    },
    {
        "code": "8469650",
        "name": "КРОНШТЕЙН КРЫЛА 82-8403016-Б (верт. лев. ГОРУ)",
        "article": "82-8403016-Б"
    },
    {
        "code": "8425710",
        "name": "КРОНШТЕЙН Ф80-3001011 (ГОРУ МТЗ-80) Кобрино*",
        "article": "Ф80-3001011"
    },
    {
        "code": "8499711",
        "name": "КРОНШТЕЙН Ф82-2301021 МТЗ",
        "article": "Ф82-2301021"
    },
    {
        "code": "8406964",
        "name": "КРЫЛО ЗАДНЕЕ ЛЕВОЕ УК 80-8404011-Б",
        "article": "80-8404011-Б"
    },
    {
        "code": "8406965",
        "name": "КРЫЛО ЗАДНЕЕ ПРАВОЕ УК 80-8404011-Б-01",
        "article": "80-8404011-Б-01"
    },
    {
        "code": "8445889",
        "name": "КРЫЛО ПЕРЕДНЕЕ ПЛАСТ. БЕЗ КРОНШТ.80-8403041-А-01",
        "article": "80-8403041А-01"
    },
    {
        "code": "8392003",
        "name": "КРЫЛЬЧАТКА ВОДЯНОГО НАСОСА Д-240 240-1307074 (МТЗ-80)",
        "article": "240-1307074"
    },
    {
        "code": "8392009",
        "name": "КРЫЛЬЧАТКА КПП 50-1701401 (МТЗ-80) ОАО \"МТЗ\"",
        "article": "50-1701401"
    },
    {
        "code": "8489274",
        "name": "КРЫШКА (крышки ПВМ) 50-3104051 ОАО \"МТЗ\"",
        "article": "50-3104051"
    },
    {
        "code": "8406607",
        "name": "КРЫШКА 52-1802076 ОАО \"БЗТДиА\"",
        "article": "52-1803076"
    },
    {
        "code": "8436076",
        "name": "КРЫШКА 52-2301061 ОАО \"МТЗ\"",
        "article": "52-2301061"
    },
    {
        "code": "8406953",
        "name": "КРЫШКА ВОМ 80-4202020-А 8 шлиц. (ср. 43мм/ср. 43мм) ОАО \"БЗТДиА\"",
        "article": "80-4202020"
    },
    {
        "code": "8521091",
        "name": "КРЫШКА ВОМ 90-4202020 8 шлиц. (шир. 56мм/узк. 34мм) ОАО \"БЗТДиА\"",
        "article": "90-4202020"
    },
    {
        "code": "8406856",
        "name": "КРЫШКА КПП С КУЛИСОЙ 70-1702010 ЦЕНТРАЛЬНЫЙ РЫЧАГ ОАО \"МТЗ\"",
        "article": "70-1702010"
    },
    {
        "code": "8465821",
        "name": "КРЫШКА РАДИАТОРА БОЛЬШАЯ А21-01-270 (МТЗ) Аналог",
        "article": "А21.01.270"
    },
    {
        "code": "8392116",
        "name": "КРЫШКА РАДИАТОРА МАЛАЯ А21-01-270 (МТЗ) (52-1304010)",
        "article": "А21.01.270-01"
    },
    {
        "code": "8422653",
        "name": "КРЫШКА РАСПРЕДЕЛЕНИЯ 240-1002060А шестерни ОАО \"ММЗ\"",
        "article": "240-1002060"
    },
    {
        "code": "8392120",
        "name": "КРЫШКА РУКАВА ПОЛУОСИ 50-2407028 (МТЗ-80) ОАО \"МТЗ\"",
        "article": "50-2407028"
    },
    {
        "code": "8406859",
        "name": "КРЫШКА УПРАВЛЕНИЯ РЕДУКТОРОМ 70-1723015 ОАО \"ВЗТЗЧ\"",
        "article": "70-1723015"
    },
    {
        "code": "8406869",
        "name": "ЛЕНТА ВОМ ТОРМОЗНАЯ 70-4202100 сред. 43 мм. (МТЗ-82) ОАО \"БЗТДиА\"",
        "article": "70-4202100"
    },
    {
        "code": "8461954",
        "name": "ЛЕНТА ВОМ ТОРМОЗНАЯ 70-4202100 сред. 43 мм. плетенка (МТЗ-82) Аналог",
        "article": "70-4202100"
    },
    {
        "code": "8413710",
        "name": "ЛИСТ ЗАДНИЙ 50-1002313-В (под стартер) ОАО \"ММЗ\"",
        "article": "50-1002313-В"
    },
    {
        "code": "8409953",
        "name": "ЛИСТ ЗАДНИЙ 50Л-1002313 (ПОД ПД)",
        "article": "50Л-1002313"
    },
    {
        "code": "8515874",
        "name": "ЛОНЖЕРОН ПРАВЫЙ 80-2801050 (РЗТ)",
        "article": "80-2801050"
    },
    {
        "code": "8435990",
        "name": "МАНЖЕТА 1.1-100Х125-4 240-1002305 ОАО \"ММЗ\"",
        "article": "240-1002305"
    },
    {
        "code": "8483924",
        "name": "МАНЖЕТА КЛАПАННАЯ (МАСЛОСЪЁМНЫЙ КОЛПАЧОК) (ФТОРКАУЧУК рыжая) 240-1007020 ОАО \"ММЗ\"",
        "article": "240-1007020"
    },
    {
        "code": "8411813",
        "name": "МАНЖЕТА КЛАПАННАЯ (МАСЛОСЪЁМНЫЙ КОЛПАЧОК) 240-1007020 ОАО \"ММЗ\"",
        "article": "240-1007020"
    },
    {
        "code": "8517928",
        "name": "МАНЖЕТА КЛАПАННАЯ (МАСЛОСЪЁМНЫЙ КОЛПАЧОК) 240-1007020 Аналог",
        "article": "240-1007020"
    },
    {
        "code": "8435984",
        "name": "МАНЖЕТА КРЫШКИ РАСПРЕДЕЛЕНИЯ 2.1-50Х70-4 240-1002055 ОАО \"ММЗ\"",
        "article": "240-1002055"
    },
    {
        "code": "8393634",
        "name": "МАСЛОМЕР В СБ.240-1002320-В (Щуп) ОАО \"ММЗ\"",
        "article": "240-1002320-В"
    },
    {
        "code": "8425717",
        "name": "МАСЛОМЕРНАЯ ЛИНЕЙКА КПП 70-1701415-А ОАО \"МТЗ\"",
        "article": "70-1701415"
    },
    {
        "code": "8435986",
        "name": "МАСЛООТРАЖАТЕЛЬ 50-1002066 ОАО \"ММЗ\"",
        "article": "50-1002066"
    },
    {
        "code": "8410993",
        "name": "МАСЛООТРАЖАТЕЛЬ К/ВАЛА ЗАДНИЙ 50-1005043 ОАО \"ММЗ\"",
        "article": "50-1005043"
    },
    {
        "code": "8406579",
        "name": "МАСЛООТРАЖАТЕЛЬ К/ВАЛА ПЕРЕДНИЙ 50-1005042 ОАО \"ММЗ\"",
        "article": "50-1005042"
    },
    {
        "code": "8462581",
        "name": "МАСЛОПРОВОД 240-3509150 (L=352 мм) Аналог",
        "article": "240-3509150"
    },
    {
        "code": "8440996",
        "name": "МАСЛОПРОВОД 240-3509150 (L=352 мм) ОАО \"ММЗ\"",
        "article": "240-3509150"
    },
    {
        "code": "8460663",
        "name": "МАСЛОПРОВОД 240-3509150-01 (L=410 мм) ОАО \"ММЗ\"",
        "article": "240-3509150-01"
    },
    {
        "code": "8393059",
        "name": "МАСЛОПРОВОД 240-3509150-02 смазки компрессора (L=114 мм) ОАО \"ММЗ\"",
        "article": "240-3509150-02"
    },
    {
        "code": "8425722",
        "name": "МАСЛОПРОВОД 70-1405117-Б масляного радиатора ОАО \"МТЗ\"",
        "article": "70-1405117Б"
    },
    {
        "code": "8425723",
        "name": "МАСЛОПРОВОД 70-1405120 масляного радиатора ОАО \"МТЗ\"",
        "article": "70-1405120"
    },
    {
        "code": "8433725",
        "name": "МАСЛОПРОВОД Ф80-3407720 ( М Т З ) *",
        "article": "Ф80-3407720"
    },
    {
        "code": "8393091",
        "name": "МАХОВИК 240-1005114-А1 (МТЗ-80/82) ПОД СТАРТЕР ОАО \"ММЗ\"",
        "article": "240-1005114"
    },
    {
        "code": "8393362",
        "name": "МОНОЦИКЛОН А53-21-000 (МТЗ-80/82) Гродно*",
        "article": "А53-21-000"
    },
    {
        "code": "8439078",
        "name": "МУФТА ПЕРЕКЛЮЧЕНИЯ ВОМ 50-4202046-Б-01 (МТЗ) (Мелкий шлиц) с кольцом",
        "article": "50-4202046"
    },
    {
        "code": "8462583",
        "name": "МУФТА СИЛОВАЯ 70-1721045 (МТЗ-80) Аналог (зубчатая)",
        "article": "70-1721045"
    },
    {
        "code": "8393527",
        "name": "МУФТА СИЛОВАЯ 70-1721045 (МТЗ-80) ОАО \"МТЗ\"",
        "article": "70-1721045"
    },
    {
        "code": "8540469",
        "name": "НАДПИСЬ 80-3903202 (овал МТЗ) Наклейка",
        "article": "80-3903202"
    },
    {
        "code": "8532550",
        "name": "НАДПИСЬ ФН-3900001",
        "article": "(БЕЛАРУС)"
    },
    {
        "code": "8486646",
        "name": "НАКЛАДКА А13.33.002 педали сце и тор правая ООО \"ТрАз\"",
        "article": "А13.33.002"
    },
    {
        "code": "8486647",
        "name": "НАКЛАДКА А13.34.001 педали тор левая ООО \"ТрАз\"",
        "article": "А13.34.001"
    },
    {
        "code": "8460591",
        "name": "НАКЛАДКА А13.38.002",
        "article": "А13.38.002"
    },
    {
        "code": "8468104",
        "name": "НАКЛАДКА 80-6708602 (ручка двери)",
        "article": "80-6708602"
    },
    {
        "code": "8468105",
        "name": "НАКЛАДКА 80-6708603 (ручка двери)",
        "article": "80-6708603"
    },
    {
        "code": "8406852",
        "name": "НАКЛАДКА СЦЕПЛЕНИЯ Д-240 70-1601138",
        "article": "70-1601138"
    },
    {
        "code": "8394001",
        "name": "НАСОС ВОДЯНОЙ 240-1307010-А (Д-240) ОАО \"БЗА\"",
        "article": "240-1307010-А"
    },
    {
        "code": "8454363",
        "name": "НАСОС ВОДЯНОЙ 245-1307010-А1-01 ОАО \"БЗА\"",
        "article": "245-1307010-А1-01"
    },
    {
        "code": "8431976",
        "name": "НАСОС ДОЗАТОР Д100-14.20-02 (МТЗ-82) ОАО \"САЛЕО\"",
        "article": "Д100-14.20-02"
    },
    {
        "code": "8482580",
        "name": "НАСОС ДОЗАТОР Д100-14.20-02 (МТЗ-82) СООО \"ДОЗАТОР +\"",
        "article": "Д100-14.20-02"
    },
    {
        "code": "8394138",
        "name": "НАСОС МАСЛЯНЫЙ 240-1403010 (МТЗ-80) Z=36 ОАО \"БЗА\"",
        "article": "240-1403010"
    },
    {
        "code": "8454470",
        "name": "НАСОС МАСЛЯНЫЙ 50-1403010-Б1 ЕВРО-3 (Дв. 245.5) Z=28 ОАО \"БЗА\"",
        "article": "50-1403010-Б1"
    },
    {
        "code": "8394561",
        "name": "ОБОЙМА 52-1802067 ОАО \"БЗТДиА\"",
        "article": "52-1802067"
    },
    {
        "code": "8432687",
        "name": "ОБОЙМА 72-2209018 ОАО \"БЗТДиА\"",
        "article": "72-2209018"
    },
    {
        "code": "8425745",
        "name": "ОБОЙМА САЛЬНИКА 52-2301062-Б1 ОАО \"МТЗ\"",
        "article": "52-2301062"
    },
    {
        "code": "8406573",
        "name": "ОПОРА КАРТЕРА МАСЛЯНОГО 50-1002042-В (МТЗ-80/82) ОАО \"ММЗ\"",
        "article": "50-1002042-В"
    },
    {
        "code": "8425746",
        "name": "ОПОРА КУЛИСЫ КПП 70-1703210-В ОАО \"МТЗ\"",
        "article": "70-1703210"
    },
    {
        "code": "8394685",
        "name": "ОПОРА ПРОМЕЖУТОЧНАЯ 72-2209010А (МТЗ-80/82) ОАО \"БЗТДиА\"",
        "article": "72-2209010"
    },
    {
        "code": "8412000",
        "name": "ОСЬ 70-4202072Б ОАО \"БЗТДиА\"",
        "article": "70-4202072"
    },
    {
        "code": "8461959",
        "name": "ОСЬ КАЧАНИЯ 50-3000011 (МТЗ-80) Аналог",
        "article": "50-3000011"
    },
    {
        "code": "8394731",
        "name": "ОСЬ КАЧАНИЯ 50-3000011 (МТЗ-80) ОАО \"ВЗТЗЧ\"",
        "article": "50-3000011"
    },
    {
        "code": "8406612",
        "name": "ОСЬ КАЧАНИЯ 52-2301058 А (L=120 мм) (МТЗ-82) ОАО \"ВЗТЗЧ\"",
        "article": "52-230105"
    },
    {
        "code": "8445883",
        "name": "ОСЬ КАЧАНИЯ 52-2301058 А3 (L=102 мм) ОАО \"ВЗТЗЧ\" 52-2301058",
        "article": "А3"
    },
    {
        "code": "8394762",
        "name": "ОСЬ КОРОМЫСЕЛ 50-1007102 А1 ОАО \"ММЗ\"",
        "article": "50-1007102"
    },
    {
        "code": "8406870",
        "name": "ОСЬ НАВЕСКИ НИЖНЯЯ (ТЯГ ПРОДОЛЬНЫХ) 70-4605026 ОАО \"ВЗТЗЧ\"",
        "article": "70-4605026"
    },
    {
        "code": "8444607",
        "name": "ОСЬ Р70-1721023",
        "article": "Р70-1721023"
    },
    {
        "code": "8425751",
        "name": "ОСЬ С РЫЧАГОМ 70-1723020 управление редуктором ОАО \"ВЗТЗЧ\"",
        "article": "70-1723020"
    },
    {
        "code": "8462584",
        "name": "ОСЬ САТЕЛЛИТА 70-4202026 (МТЗ-80) Аналог",
        "article": "70-4202026"
    },
    {
        "code": "8394787",
        "name": "ОСЬ САТЕЛЛИТА 70-4202026 (МТЗ-80) ОАО \"БЗТДиА\"",
        "article": "70-4202026"
    },
    {
        "code": "8432685",
        "name": "ОТВОДКА С ПОДШИПНИКОМ 50-1601180-А d145х55, 1.28кг. (МТЗ-80/82/1221/1523/2022) ОАО \"БЗТДиА\"",
        "article": "50-1601180"
    },
    {
        "code": "8406961",
        "name": "ОТОПИТЕЛЬ КАБИНЫ УК СБ ОТОПИТЕЛЬ 1522-8101100 (МТЗ 82-1523)",
        "article": "1522-8101100"
    },
    {
        "code": "8451887",
        "name": "ОТОПИТЕЛЬ КАБИНЫ УНИВЕРСАЛЬНЫЙ 12V 1221-00.000",
        "article": "1221-00.000"
    },
    {
        "code": "8484656",
        "name": "ОТРАЖАТЕЛЬ 240-1105025 (сеточка фильтра топл. грубой очистки) ОАО \"БЗА\"",
        "article": "240-1105025"
    },
    {
        "code": "8482164",
        "name": "ПАЛЕЦ 8х30 ОСТ 37.001.163-75 915306 ОАО \"МТЗ\"",
        "article": "915306"
    },
    {
        "code": "8412103",
        "name": "ПАЛЕЦ А61.10.001 (МТЗ- 82.1-1221) СМ КОД 8425753",
        "article": "А61.10.001"
    },
    {
        "code": "8481194",
        "name": "ПАЛЕЦ 50-3405033-А ОАО \"БЗТДиА\"",
        "article": "50-3405033"
    },
    {
        "code": "8436605",
        "name": "ПАЛЕЦ 50-4605049-Б ОАО \"САЗ\"",
        "article": "50-4605049"
    },
    {
        "code": "8436534",
        "name": "ПАЛЕЦ 50-4605076 ОАО \"ВЗТЗЧ\"",
        "article": "50-4605076"
    },
    {
        "code": "8431920",
        "name": "ПАЛЕЦ А61.03.001-01 ОАО \"САЗ\"",
        "article": "А61.03.001-01"
    },
    {
        "code": "8461481",
        "name": "ПАЛЕЦ А61.03.001-02 в тягу центральную стопорный ОАО \"САЗ\"",
        "article": "А61.03.001-02"
    },
    {
        "code": "8536269",
        "name": "ПАЛЕЦ А61.03.001-02 в тягу центральную стопорный в сборе с цепью d-22мм Аналог",
        "article": "А61.03.001-02"
    },
    {
        "code": "8425753",
        "name": "ПАЛЕЦ А61.10.001 (МТЗ-82) тяги центральной длин.",
        "article": "А61.10.001"
    },
    {
        "code": "8406405",
        "name": "ПАЛЕЦ МАХОВИКА (КРЕПЛЕНИЯ КОРЗИНЫ СЦ) 240-1005122 ОАО \"ММЗ\"",
        "article": "240-1005122"
    },
    {
        "code": "8436208",
        "name": "ПАЛЕЦ ОТЖИМНОГО РЫЧАГА 70-1601096 (МТЗ-82/1025/1221/1523) ОАО \"БЗТДиА\"",
        "article": "70-1601096"
    },
    {
        "code": "8431921",
        "name": "ПАЛЕЦ ПОПЕРЕЧИНЫ А61.10.002 ОАО \"ВЗТЗЧ\"",
        "article": "А61.10.002"
    },
    {
        "code": "8436615",
        "name": "ПАЛЕЦ РУЛЕВОЙ 1220-3003021",
        "article": "1220-3003021"
    },
    {
        "code": "8482162",
        "name": "ПАЛЕЦ С80-4607088 ОАО \"МТЗ\"",
        "article": "С80-4607088"
    },
    {
        "code": "8425752",
        "name": "ПАЛЕЦ Ф50-4605084 тяга нижняя ОАО \"МТЗ\"",
        "article": "Ф50-4605084"
    },
    {
        "code": "8452820",
        "name": "ПАЛЕЦ Ф80-3405101-Б ЗИ ОАО \"ВЗТЗЧ\"",
        "article": "Ф80-3405101-Б"
    },
    {
        "code": "8394969",
        "name": "ПАЛЕЦ ШАРОВЫЙ А35-32-002-А (МТЗ)",
        "article": "А35-32-002-А"
    },
    {
        "code": "8472439",
        "name": "ПАТРУБОК 243-1109210 ОАО \"ММЗ\"",
        "article": "243-1109210"
    },
    {
        "code": "8425759",
        "name": "ПАТРУБОК 70-8115022-А (МТЗ) ГБЦ (задний под кран отопителя) ООО \"ТрАз\"",
        "article": "70-8115022-А"
    },
    {
        "code": "8463175",
        "name": "ПАТРУБОК ВОДЯНОГО НАСОСА 50-1307044 (МТЗ-80/82) ООО \"ТрАз\"",
        "article": "50-1307044"
    },
    {
        "code": "8422475",
        "name": "ПАТРУБОК МАСЛ. НАСОСА ОТВОДЯЩИЙ 50-1403015 (МТЗ-82) ОАО \"ММЗ\"",
        "article": "50-1403015"
    },
    {
        "code": "8430697",
        "name": "ПАТРУБОК С ЗАСЛОНКОЙ 240-1003220-В ОАО \"ММЗ\"",
        "article": "240-1003220-В"
    },
    {
        "code": "8457722",
        "name": "ПЕДАЛЬ 80-4803170 ОАО \"МТЗ\"",
        "article": "80-4803170"
    },
    {
        "code": "8441138",
        "name": "ПЕРЕХОДНИК 245-1008021 Д-245 ОАО \"ММЗ\"",
        "article": "245-1008021"
    },
    {
        "code": "8424177",
        "name": "ПЕРЕХОДНИК 70-2409026-Б (дифференциала) ОАО \"МТЗ\"",
        "article": "70-2409026-Б"
    },
    {
        "code": "8395325",
        "name": "ПЕРЕХОДНИК КОЛЛЕКТОРА (ГЛУШИТЕЛЯ) МТЗ 240-1008021-Б1 ОАО \"ММЗ\"",
        "article": "240-1008021-Б1"
    },
    {
        "code": "8443861",
        "name": "ПЕТЛЯ 80-6707010",
        "article": "80-6707010"
    },
    {
        "code": "8467295",
        "name": "ПЕТЛЯ 80-6707013 ОАО \"ВЗТЗЧ\"",
        "article": "80-6707013"
    },
    {
        "code": "8467296",
        "name": "ПЕТЛЯ 80-6708902 ОАО \"ВЗТЗЧ\"",
        "article": "80-6708902"
    },
    {
        "code": "8471148",
        "name": "ПЛАНКА 240-3701063 ОАО \"ММЗ\"",
        "article": "240-3701063"
    },
    {
        "code": "8452804",
        "name": "ПЛАНКА 70-3407146**",
        "article": "70-3407146"
    },
    {
        "code": "8564877",
        "name": "ПЛАСТИНА 50-4604044-Б",
        "article": "50-4604044-Б"
    },
    {
        "code": "8564878",
        "name": "ПЛАСТИНА 70-4608072",
        "article": "70-4608072"
    },
    {
        "code": "8484473",
        "name": "ПЛИТА Ф80-3407031 под насос дозатор ОАО \"БЗТДиА\"",
        "article": "Ф80-3407031"
    },
    {
        "code": "8440921",
        "name": "ПОВОДОК 50-1702095-А1 ОАО \"МТЗ\"",
        "article": "50-1702095-А1"
    },
    {
        "code": "8563552",
        "name": "ПОДУШКА 130-5001332 (МТЗ-80) ООО \"ТрАз\"",
        "article": "130-5001332"
    },
    {
        "code": "8530021",
        "name": "ПОДУШКА СИДЕНЬЯ ВЕРХ. 80В-6805001",
        "article": "80В-6805001"
    },
    {
        "code": "8530025",
        "name": "ПОДУШКА СИДЕНЬЯ НИЖ. 80В-6804007",
        "article": "80В-6804007"
    },
    {
        "code": "8396623",
        "name": "ПОЛУОСЬ ЗАДНЯЯ 50-2407082А (МАРЗ) (МТЗ-80/82 со шлицами)",
        "article": "50-2407082"
    },
    {
        "code": "8433643",
        "name": "ПОЛУОСЬ ЗАДНЯЯ 50-2407082А-01 Н/О (МАРЗ) (МТЗ-80/82 без шллицов)",
        "article": "50-2407082А-01"
    },
    {
        "code": "8461962",
        "name": "ПОЛУОСЬ ПЕРЕДНЯЯ 52-2308065 (МТЗ-82) Аналог",
        "article": "52-2308065"
    },
    {
        "code": "8396641",
        "name": "ПОЛУОСЬ ПЕРЕДНЯЯ 52-2308065 (МТЗ-82) ОАО \"МТЗ\"",
        "article": "52-2308065"
    },
    {
        "code": "8395690",
        "name": "ПОЛУОСЬ ЦАПФЫ ЛЕВАЯ 70-3001067 ОАО \"МЗШ\"",
        "article": "70-3001067"
    },
    {
        "code": "8396633",
        "name": "ПОЛУОСЬ ЦАПФЫ ПРАВ 70-3001067-01 ОАО \"МЗШ\"",
        "article": "70-3001067-01"
    },
    {
        "code": "8396655",
        "name": "ПОПЕРЕЧИНА 80-4605025 В СБ. (МТЗ-80/82) ОАО \"ВЗТЗЧ\"",
        "article": "80-4605025"
    },
    {
        "code": "8468106",
        "name": "ПОРУЧЕНЬ 80-6708610 (ручка двери)",
        "article": "80-6708610"
    },
    {
        "code": "8530019",
        "name": "ПОРУЧЕНЬ 80-6708610 (ручка двери)",
        "article": "80-6708610"
    },
    {
        "code": "8462589",
        "name": "ПОРШЕНЬ ПД Н1 Д24С06Б Аналог",
        "article": "Д24.023-Г"
    },
    {
        "code": "8396907",
        "name": "ПРИВОД РУЛЕВОЙ 80-3401010 (МТЗ-80) ОАО \"БЗТДиА\" (ГУР)",
        "article": "80-3401010"
    },
    {
        "code": "8454416",
        "name": "ПРОБКА 1 1/4 70-1701300 ОАО \"МТЗ\"",
        "article": "70-1701300"
    },
    {
        "code": "8441486",
        "name": "ПРОБКА 240-1003281 ОАО \"ММЗ\"",
        "article": "240-1003281"
    },
    {
        "code": "8435454",
        "name": "ПРОБКА 50-3407050 (ГУР) ОАО \"БЗТДиА\"",
        "article": "50-3407050"
    },
    {
        "code": "8412091",
        "name": "ПРОБКА МАСЛОЗАЛИВНОЙ ГОРЛОВИНЫ А19-01-001 (МТЗ-80/1221) ООО \"ТрАз\"",
        "article": "А19-01-001"
    },
    {
        "code": "8483358",
        "name": "ПРОБКА ПК КГ 3/4\" ОАО \"МТЗ\" ПК КГ",
        "article": "3/4\""
    },
    {
        "code": "8421488",
        "name": "ПРОБКА РАДИАТОРА ОТОПИТЕЛЯ 80-8100052",
        "article": "80-8100052"
    },
    {
        "code": "8491882",
        "name": "ПРОБКА САПУНА 50-4608059 ОАО \"МТЗ\"",
        "article": "50-4608059"
    },
    {
        "code": "8465822",
        "name": "ПРОБКА ТОПЛИВНОГО БАКА 082-1103010 АЛЮМ (МТЗ) Аналог",
        "article": "082-1103010"
    },
    {
        "code": "8463176",
        "name": "ПРОБКА ТОПЛИВНОГО БАКА 082-1103010 ПЛ.(МТЗ) Аналог",
        "article": "082-1103010"
    },
    {
        "code": "8397397",
        "name": "ПРОУШИНА 70-4605048-А нижней тяги ОАО \"САЗ\"",
        "article": "70-4605048"
    },
    {
        "code": "8488547",
        "name": "ПРУЖИНА 50-4608057 (рулевого управ.) ОАО \"МТЗ\"",
        "article": "50-4608057"
    },
    {
        "code": "8457528",
        "name": "ПРУЖИНА 54-06-448-А ОАО \"МТЗ\"",
        "article": "54-06-448-А"
    },
    {
        "code": "8460293",
        "name": "ПРУЖИНА 70-4616033",
        "article": "70-4616033"
    },
    {
        "code": "8397465",
        "name": "ПРУЖИНА КЛАПАНА ВНУТР. 240-1007046 А1 ОАО \"ММЗ\"",
        "article": "240-1007046"
    },
    {
        "code": "8397466",
        "name": "ПРУЖИНА КЛАПАНА НАРУЖ. 240-1007045 А1 ОАО \"ММЗ\"",
        "article": "240-1007045"
    },
    {
        "code": "8406880",
        "name": "ПРУЖИНА ТАРЕЛЬЧАТАЯ 72-2209021 ОАО \"БЗТДиА\"",
        "article": "72-2209021"
    },
    {
        "code": "8397495",
        "name": "ПРУЖИНА ТОРМОЗНОГО ДИСКА (3 витка) 50-3502068 **",
        "article": "50-3502068"
    },
    {
        "code": "8397798",
        "name": "РАЗДАТОЧНАЯ КОРОБКА С МУФТОЙ 72-1802020 ОАО \"БЗТДиА\"",
        "article": "72-1802020"
    },
    {
        "code": "8406959",
        "name": "РАМКА БОКОВАЯ УК В СБОРЕ 80-6708110 ОАО \"МТЗ\"",
        "article": "80-6708110"
    },
    {
        "code": "8397862",
        "name": "РАСКОС 80-4605150-02 РЕГ ПРАВЫЙ (МТЗ-80/82) ОАО \"ВЗТЗЧ\"",
        "article": "80-4605150-02"
    },
    {
        "code": "8577400",
        "name": "РЕМКОМПЛЕКТ Дифф-ла з/м",
        "article": "МР"
    },
    {
        "code": "8557321",
        "name": "РЕМКОМПЛЕКТ КОРЗИНЫ СЦЕПЛЕНИЯ 70-1601090 (РМ70.090) ОАО \"БЗТДиА\"",
        "article": "РМ70.090"
    },
    {
        "code": "8461493",
        "name": "РЕМКОМПЛЕКТ КОРЗИНЫ СЦЕПЛЕНИЯ 85-1601090 (РМ85.090) ОАО \"БЗТДиА",
        "article": "РМ85.090"
    },
    {
        "code": "8517930",
        "name": "РЕМКОМПЛЕКТ НАКОНЕЧНИКА РУЛЕВОЙ ТЯГИ С ПАЛЬЦЕМ И ГАЙКОЙ (МТЗ-80,ЮМЗ) (717)",
        "article": "Аналог"
    },
    {
        "code": "8515882",
        "name": "РЕМКОМПЛЕКТ ПАЛЬЦА Ц-50 102-3405103 (КОРОТКИЙ 130 ММ) МТЗ 82 (РЗТ)",
        "article": "102-3405103-Б"
    },
    {
        "code": "8515883",
        "name": "РЕМКОМПЛЕКТ ПАЛЬЦА Ц-50 102-3405103-Б (ДЛИННЫЙ 142 ММ) МТЗ 82 (РЗТ)",
        "article": "102-3405103"
    },
    {
        "code": "8412089",
        "name": "РЕШЕТКА ВЕРХНЯЯ 90-8401120 (МТЗ-1221)",
        "article": "90-8401120"
    },
    {
        "code": "8406963",
        "name": "РЕШЕТКА КАПОТА МТЗ 80-8401070 ВЕРХНЯЯ В СБ. ОАО \"МТЗ\"",
        "article": "80-8401070"
    },
    {
        "code": "8422083",
        "name": "РЕШЕТКА НИЖНИХ ФАР 80-8401080 (КРУГЛЫЕ) ОАО \"МТЗ\"",
        "article": "80-8401080"
    },
    {
        "code": "8443192",
        "name": "РЕШЕТКА НИЖНИХ ФАР 90-8401080 (МТЗ-900 серии)",
        "article": "90-8401080"
    },
    {
        "code": "8396415",
        "name": "РОЛИК 4х34.8А3 (ХОДОУМЕНЬШИТЕЛЬ МТЗ). 922207 МТЗ*(47)",
        "article": "922207"
    },
    {
        "code": "8406609",
        "name": "РОЛИКОВ КОМПЛЕКТ РАЗДАТ. КОРОБКИ 52-1802110А (8 ШТ.) ОАО \"БЗТДиА\"",
        "article": "52-1802110"
    },
    {
        "code": "8469002",
        "name": "РУЧКА ДВЕРИ ЛЕВАЯ 80-6105300 с ключом Аналог",
        "article": "80-6105300"
    },
    {
        "code": "8411992",
        "name": "РЫЧАГ 70-3503017-А ОАО \"МТЗ\"",
        "article": "70-3503017"
    },
    {
        "code": "8490108",
        "name": "РЫЧАГ 70-3507130 (ручник) ОАО \"МТЗ\"",
        "article": "70-3507130"
    },
    {
        "code": "8480627",
        "name": "РЫЧАГ 70-4216050-Б ОАО \"МТЗ\"",
        "article": "70-4216050-Б"
    },
    {
        "code": "8432686",
        "name": "РЫЧАГ 72-1802082 ОАО \"БЗТДиА\"",
        "article": "72-1802082"
    },
    {
        "code": "8462595",
        "name": "РЫЧАГ ОТЖИМНОЙ 70-1601095 В СБ. (МТЗ-80) Аналог",
        "article": "70-1601095"
    },
    {
        "code": "8461964",
        "name": "РЫЧАГ ОТЖИМНОЙ В СБ. 85-1601095 (МТЗ-82/1221/1523) Аналог",
        "article": "85-1601095"
    },
    {
        "code": "8433823",
        "name": "РЫЧАГ ОТЖИМНОЙ В СБ. 85-1601095 (МТЗ-82/1221/1523) ОАО \"БЗТДиА\"",
        "article": "85-1601095"
    },
    {
        "code": "8399633",
        "name": "РЫЧАГ ПВМ 52-2308074-01 (МТЗ) ГУР правый ОАО \"БЗТДиА\"",
        "article": "52-2308074-01"
    },
    {
        "code": "8413963",
        "name": "РЫЧАГ ПВМ 52-2308075-01 (МТЗ) ГУР левый ОАО \"БЗТДиА\"",
        "article": "52-2308075-01"
    },
    {
        "code": "8399644",
        "name": "РЫЧАГ ПВМ 72-2308074 (МТЗ) ГОРУ правый ОАО \"БЗТДиА\"",
        "article": "72-2308074"
    },
    {
        "code": "8433641",
        "name": "РЫЧАГ ПВМ 72-2308075-01 (МТЗ) ГОРУ левый ОАО \"БЗТДиА\"",
        "article": "72-2308075-01"
    },
    {
        "code": "8470949",
        "name": "РЫЧАГ ПЕРЕКЛЮЧЕНИЯ КП 70-1703220А (МТЗ-82 боковой)",
        "article": "70-1703220"
    },
    {
        "code": "8418147",
        "name": "РЫЧАГ ПОВОРОТНЫЙ ЦАПФЫ 50-3001040 А1 ГУР (МТЗ-80) правый, левый ОАО \"ВЗТЗЧ\"",
        "article": "50-3001040"
    },
    {
        "code": "8399643",
        "name": "РЫЧАГ ПОВОРОТНЫЙ 70-4605024-А средний ОАО \"САЗ\"",
        "article": "70-4605024"
    },
    {
        "code": "8460475",
        "name": "САТЕЛЛИТ ВОМ 70-4202024 (МТЗ-80) Аналог",
        "article": "70-4202024"
    },
    {
        "code": "8399848",
        "name": "САТЕЛЛИТ ВОМ 70-4202024 (МТЗ-80) ОАО \"МЗШ\"",
        "article": "70-4202024"
    },
    {
        "code": "8399853",
        "name": "САТЕЛЛИТ С ВТУЛКОЙ 85-2403055 ОАО \"МЗШ\"",
        "article": "85-2403055"
    },
    {
        "code": "8400092",
        "name": "СЕДЛО КЛАПАНА ВПУСКНОГО 245-1003018 ОАО \"ММЗ\"",
        "article": "245-1003018"
    },
    {
        "code": "8400093",
        "name": "СЕДЛО КЛАПАНА ВЫПУСКНОГО 245-1003019 ОАО \"ММЗ\"",
        "article": "245-1003019"
    },
    {
        "code": "8482670",
        "name": "СЕРЬГА 115 СТЯЖКИ А61-09-002 Аналог",
        "article": "А61-09-002"
    },
    {
        "code": "8451494",
        "name": "СЕРЬГА 115 СТЯЖКИ А61-09-002 В СБ. Аналог",
        "article": "А61-09-002"
    },
    {
        "code": "8400133",
        "name": "СЕРЬГА 70-4605330 (МТЗ)",
        "article": "70-4605330"
    },
    {
        "code": "8411913",
        "name": "СЕТКА 240-1002085 ОАО \"ММЗ\"",
        "article": "240-1002085"
    },
    {
        "code": "8461972",
        "name": "СЕТКА ФИЛЬТРУЮЩАЯ 240-1404110 (МТЗ) грубой очистки Аналог",
        "article": "240-1404110"
    },
    {
        "code": "8406461",
        "name": "СИДЕНЬЕ 80-6800010 ОАО \"БЗТДиА\"",
        "article": "80-6800010"
    },
    {
        "code": "8469417",
        "name": "СИДЕНЬЕ 80В-6800000 В СБ. Аналог",
        "article": "80В680000"
    },
    {
        "code": "8415253",
        "name": "СТАКАН 52-2302016-А ГЛ. ПЕРЕДАЧИ ПВМ (МТЗ-82/1221/1523)",
        "article": "52-2302016"
    },
    {
        "code": "8400481",
        "name": "СТАКАН ПЕРВИЧНОГО ВАЛА 50-1701034 (МТЗ-80) ОАО \"МТЗ\"",
        "article": "50-1701034"
    },
    {
        "code": "8406571",
        "name": "СТАКАН ПОДШИПНИКА ЗАДНЕГО МОСТА 50Х-2407042 ОАО \"МТЗ\"",
        "article": "50Х-2407042"
    },
    {
        "code": "8437762",
        "name": "СТАКАН ПОДШИПНИКА С КОЛЬЦОМ И ПОДШИП В СБ. 50-4202040 ОАО \"БЗТДиА\"",
        "article": "50-4202040"
    },
    {
        "code": "8406591",
        "name": "СТАКАН ШЕСТЕРНИ (1198) 50-1701195 ОАО \"МТЗ\"",
        "article": "50-1701195"
    },
    {
        "code": "8433642",
        "name": "СТОЙКА ОСИ КОРОМЫСЕЛ СРЕД. 240-1007152-Б (с заглушкой) ОАО \"ММЗ\"",
        "article": "240-1007152-Б"
    },
    {
        "code": "8400938",
        "name": "СТУПИЦА 50/70 -1601142 А 50/70",
        "article": "-1601142"
    },
    {
        "code": "8400939",
        "name": "СТУПИЦА 70-1601051",
        "article": "70-1601051"
    },
    {
        "code": "8400883",
        "name": "СТУПИЦА ЗАД КОЛЕСА (С БОЛТОМ) 70-3104010 (50-3104010-А1) ОАО \"САЗ\"",
        "article": "70-3104010"
    },
    {
        "code": "8400917",
        "name": "СТУПИЦА ПЕРЕДНЯЯ С ПОДШИПНИКОМ 70-3103010 (МТЗ-80) Кобрино",
        "article": "70-3103010"
    },
    {
        "code": "8402006",
        "name": "СТЯЖКА А61-04-000 80-4605080 (МТЗ-80/82) ОАО \"ВЗТЗЧ\"",
        "article": "80-4605080"
    },
    {
        "code": "8519047",
        "name": "СТЯЖКА А61-04-000 80-4605080 (МТЗ-80/82) (РЗТ)",
        "article": "80-4605080"
    },
    {
        "code": "8400951",
        "name": "СТЯЖКА А61-04-003 БЕЗ ВИНТОВ И ГАЕК",
        "article": "А61-04-003"
    },
    {
        "code": "8410793",
        "name": "СТЯЖКА РАСКОСА 012 А61-02-001 ОАО \"САЗ\"",
        "article": "А61-02-001"
    },
    {
        "code": "8400960",
        "name": "СТЯЖКА С КРОНШТЕЙНОМ 50-4605115 (МТЗ-80) ОАО \"ВЗТЗЧ\"",
        "article": "50-4605115"
    },
    {
        "code": "8406584",
        "name": "СУХАРЬ КЛАПАНА 50-1007053 А2 ОАО \"ММЗ\"",
        "article": "50-1007053"
    },
    {
        "code": "8401070",
        "name": "ТАРЕЛКА ПРУЖИНЫ КЛАПАНА 240-1007048 ОАО \"ММЗ\"",
        "article": "240-1007048"
    },
    {
        "code": "8414786",
        "name": "ТОЛКАТЕЛЬ 240-1007375 (МТЗ-80/1221) ОАО \"ММЗ\"",
        "article": "240-1007375"
    },
    {
        "code": "8406462",
        "name": "ТОПЛИВОПРОВОД 240-1104320- А2 ОАО \"ММЗ\"",
        "article": "240-1104320"
    },
    {
        "code": "8472745",
        "name": "ТОПЛИВОПРОВОД 240-1104320- В ОАО \"ММЗ\" (4 отв. 10 мм. гнутый)",
        "article": "240-1104320"
    },
    {
        "code": "8462603",
        "name": "ТОПЛИВОПРОВОД 70-1101345-Б1 Аналог",
        "article": "70-1101345-Б1"
    },
    {
        "code": "8407670",
        "name": "ТОПЛИВОПРОВОД 70-1101345-Б1 ОАО \"БЗТДиА\" (от баков) ПВХ",
        "article": "70-1101345-Б1"
    },
    {
        "code": "8433821",
        "name": "ТОПЛИВОПРОВОД 70-1104180 (обратка 10 мм) ОАО \"БЗТДиА\"",
        "article": "70-1104180"
    },
    {
        "code": "8545351",
        "name": "ТОПЛИВОПРОВОД 920-1101160-01 (обратка 8/10 мм) L-2178 мм Резин ОАО \"БЗТДиА\"",
        "article": "920-1101160-01"
    },
    {
        "code": "8425798",
        "name": "ТРОС АВАРИЙНОГО ОСТАНОВА ДВИГАТЕЛЯ 70-1024300 1133 мм ОАО \"МТЗ\"",
        "article": "70-1024300"
    },
    {
        "code": "8469353",
        "name": "ТРОС УПРАВЛЕНИЯ БЛОКИРОВКОЙ ДИФФЕРЕНЦИАЛА 70-4803050 (МТЗ) (С наконечником)",
        "article": "70-4803050"
    },
    {
        "code": "8493040",
        "name": "ТРУБА 80-8201106-А (кронштейн зеркала) ОАО \"МТЗ\"",
        "article": "80-8201106-А"
    },
    {
        "code": "8461967",
        "name": "ТРУБА ШКВОРНЯ 72-2308030-А Аналог",
        "article": "72-2308030-А"
    },
    {
        "code": "8406885",
        "name": "ТРУБА ШКВОРНЯ 72-2308030-А ОАО \"МТЗ\"",
        "article": "72-2308030-А"
    },
    {
        "code": "8401810",
        "name": "ТРУБКА МАНОМЕТРА (ДАВЛЕНИЯ МАСЛА) 70-3801080 (МТЗ-80)",
        "article": "70-3801080"
    },
    {
        "code": "8462604",
        "name": "ТРУБКА МАНОМЕТРА (ДАВЛЕНИЯ МАСЛА) 70-3801080 (МТЗ-80) Аналог",
        "article": "70-3801080"
    },
    {
        "code": "8425803",
        "name": "ТРУБКА Н80-4607160 (МТЗ)",
        "article": "Н80-4607160"
    },
    {
        "code": "8461969",
        "name": "ТРУБКА ТОПЛИВНАЯ ВЫСОКОГО ДАВЛЕНИЯ 240-1104300-(01-04) (комплект) Аналог",
        "article": "240-1104300-(01-04)"
    },
    {
        "code": "8401836",
        "name": "ТРУБКА ТОПЛИВНАЯ ВЫСОКОГО ДАВЛЕНИЯ 240-1104300-01 ОАО \"ММЗ\"",
        "article": "240-1104300-01"
    },
    {
        "code": "8401837",
        "name": "ТРУБКА ТОПЛИВНАЯ ВЫСОКОГО ДАВЛЕНИЯ 240-1104300-02 ОАО \"ММЗ\"",
        "article": "240-1104300-02"
    },
    {
        "code": "8401838",
        "name": "ТРУБКА ТОПЛИВНАЯ ВЫСОКОГО ДАВЛЕНИЯ 240-1104300-03 ОАО \"ММЗ\"",
        "article": "240-1104300-03"
    },
    {
        "code": "8401839",
        "name": "ТРУБКА ТОПЛИВНАЯ ВЫСОКОГО ДАВЛЕНИЯ 240-1104300-04 ОАО \"ММЗ\"",
        "article": "240-1104300-04"
    },
    {
        "code": "8462602",
        "name": "ТРУБКА ТОПЛИВНАЯ НИЗКОГО ДАВЛЕНИЯ 240-1104160-03 короткая Аналог",
        "article": "240-1104160-03"
    },
    {
        "code": "8499900",
        "name": "ТРУБКА ТОПЛИВНАЯ НИЗКОГО ДАВЛЕНИЯ 245-1104180-А1 L=205 мм ОАО \"ММЗ\"",
        "article": "245-1104180-А1"
    },
    {
        "code": "8437734",
        "name": "ТРУБКА ТОПЛИВНАЯ НИЗКОГО ДАВЛЕНИЯ 245-1104180-А1-01 L=305 мм ОАО \"ММЗ\"",
        "article": "245-1104180-А1-01"
    },
    {
        "code": "8465878",
        "name": "ТРУБКА ТОПЛИВНАЯ НИЗКОГО ДАВЛЕНИЯ 245-1104180-А1-03 L=455 мм ОАО \"ММЗ\"",
        "article": "245-1104180-А1-03"
    },
    {
        "code": "8467905",
        "name": "ТРУБКА ТОПЛИВНАЯ НИЗКОГО ДАВЛЕНИЯ 245-1104180-А1-06 L=1045 мм ОАО \"ММЗ\"",
        "article": "245-1104180-А1-06"
    },
    {
        "code": "8487181",
        "name": "ТРУБОПРОВОД 242-3707130-Б ОАО \"ММЗ\"",
        "article": "242-3707130-Б"
    },
    {
        "code": "8402004",
        "name": "ТЯГА ЗАДНЕЙ НАВЕСКИ (ЛЕВАЯ МАЛАЯ) 80-4605040-01 ОАО \"САЗ\"",
        "article": "80-4605040-01"
    },
    {
        "code": "8402003",
        "name": "ТЯГА ЗАДНЕЙ НАВЕСКИ (ПРАВАЯ МАЛАЯ) 80-4605040 ОАО \"САЗ\"",
        "article": "80-4605040"
    },
    {
        "code": "8402001",
        "name": "ТЯГА ПЕРЕДНЯЯ 70-4605050 (ПРАВАЯ ДЛИННАЯ) ОАО \"САЗ\"",
        "article": "70-4605050"
    },
    {
        "code": "8461970",
        "name": "ТЯГА РУЛЕВАЯ ДЛИН. 50-3003010А4 В СБ. (L=330 мм) (МТЗ-80) ГУР Аналог",
        "article": "50-3003010А4"
    },
    {
        "code": "8462606",
        "name": "ТЯГА РУЛЕВАЯ КОРОТКАЯ 52-3003010А2 (L=280 мм) (МТЗ-82) ГУР Аналог",
        "article": "52-3003010А2"
    },
    {
        "code": "8433734",
        "name": "ТЯГА УПР. РАСПРЕД. 80-4607087-01 ОАО \"МТЗ\"",
        "article": "80-4607087-01"
    },
    {
        "code": "8411995",
        "name": "УГОЛЬНИК 70-3506033 ОАО \"МТЗ\"",
        "article": "70-3506033"
    },
    {
        "code": "8411998",
        "name": "УГОЛЬНИК 70-3513015 ОАО \"МТЗ\"",
        "article": "70-3513015"
    },
    {
        "code": "8467600",
        "name": "УГОЛЬНИК ПОВОРОТНЫЙ С ГАЙКОЙ 240-1104118 (СТАЛЬНОЙ) Аналог",
        "article": "240-1104118"
    },
    {
        "code": "8407060",
        "name": "УПЛОТНЕНИЕ МАСЛЯНОГО КАРТЕРА ЗАДНЕЕ 240-1401065 ООО \"ТрАз\"",
        "article": "240-1401065"
    },
    {
        "code": "8407059",
        "name": "УПЛОТНЕНИЕ МАСЛЯНОГО КАРТЕРА ПЕРЕДНЕЕ (короткая) 240-1401059 ООО \"ТрАз\"",
        "article": "240-1401059"
    },
    {
        "code": "8468004",
        "name": "УПЛОТНИТЕЛЬ 80-6700021-01 задней рамки (МТЗ-80/82/1221) L 4080 ООО \"ТрАз\"",
        "article": "80-6700021-01"
    },
    {
        "code": "8500363",
        "name": "УПЛОТНИТЕЛЬ 80-6700021-02 задней рамки (МТЗ-80/82/1221) L 2960 ООО \"ТрАз\"",
        "article": "80-6700021-02"
    },
    {
        "code": "8474499",
        "name": "УПЛОТНИТЕЛЬ 80-6700021-А двери кабины УК (МТЗ-80/82/1221) L-4000 ООО \"ТрАз\"",
        "article": "80-6700021-А"
    },
    {
        "code": "8437410",
        "name": "УПЛОТНИТЕЛЬ ЗАД. СТЕКЛА МТЗ ПРОФИЛЬ А-37.08.043-05 (L-3870 мм)",
        "article": "А-37.08.043-05"
    },
    {
        "code": "8536533",
        "name": "УПЛОТНИТЕЛЬ КРЫЛА 80-8404013-А (крыло-кабина) (L-1120 мм) ООО \"ТрАз\"",
        "article": "80-8404013-А"
    },
    {
        "code": "8471290",
        "name": "УПЛОТНИТЕЛЬ СТЕКЛА МТЗ ПРОФИЛЬ А-37.08.043-01 (L=4200 мм) ПЕРЕДНЕЕ СТЕКЛО",
        "article": "А-37.08.043-01"
    },
    {
        "code": "8471298",
        "name": "УПЛОТНИТЕЛЬ СТЕКЛА МТЗ ПРОФИЛЬ А-37.08.043-03 (L=1670 мм)",
        "article": "А-37.08.043-03"
    },
    {
        "code": "8411000",
        "name": "УПЛОТНИТЕЛЬ ШАРНИРА Ф80-3405109 ООО \"ТрАз\"",
        "article": "Ф80-3405109"
    },
    {
        "code": "8460009",
        "name": "УПОР 50-1602027 ОАО \"МТЗ\"",
        "article": "50-1602027"
    },
    {
        "code": "8412463",
        "name": "УПОР 50-1701187 ОАО \"МТЗ\"",
        "article": "50-1701187"
    },
    {
        "code": "8402365",
        "name": "УТЕПЛИТЕЛЬ КАПОТА (МТЗ-82) Н/О ВСТР.",
        "article": "ФАРЫ"
    },
    {
        "code": "8497713",
        "name": "УТЕПЛИТЕЛЬ КАПОТА (МТЗ-892,920,922,952,1021,1025)",
        "article": "ст/обр"
    },
    {
        "code": "8425811",
        "name": "УШКО (СТАКАН) 70-4216013 (МТЗ) управление задним ВОМ",
        "article": "70-4216013"
    },
    {
        "code": "8441487",
        "name": "ФИКСАТОР 240-1007185 ОАО \"ММЗ\"",
        "article": "240-1007185"
    },
    {
        "code": "8532606",
        "name": "ФИКСАТОР 80-6708960 (ручка бокового стекла в сб)",
        "article": "80-6708960"
    },
    {
        "code": "8402485",
        "name": "ФИЛЬТР МАСЛЯНЫЙ 240-1404010 (ЦЕНТРИФУГА) (МТЗ-80) ОАО \"БЗА\"",
        "article": "240-1404010"
    },
    {
        "code": "8425812",
        "name": "ФИЛЬТР САПУНА 240-1002440 (МТЗ-82) ОАО \"ММЗ\"",
        "article": "240-1002440"
    },
    {
        "code": "8407907",
        "name": "ФИЛЬТР ТОПЛИВНЫЙ ГРУБОЙ ОЧИСТКИ 240-1105010 Аналог",
        "article": "240-1105010"
    },
    {
        "code": "8413932",
        "name": "ФИЛЬТР ТОПЛИВНЫЙ ГРУБОЙ ОЧИСТКИ 240-1105010 ОАО \"ММЗ\"",
        "article": "240-1105010"
    },
    {
        "code": "8447238",
        "name": "ФИЛЬТР ТОПЛИВНЫЙ ТОНКОЙ ОЧИСТКИ МТЗ 240-1117010-А ОАО \"ММЗ\"",
        "article": "240-1117010-А"
    },
    {
        "code": "8462607",
        "name": "ФЛАНЕЦ 52-1802078 Аналог",
        "article": "52-1802078"
    },
    {
        "code": "8402592",
        "name": "ФЛАНЕЦ 52-1802078 ОАО \"БЗТДиА\"",
        "article": "52-1802078"
    },
    {
        "code": "8406886",
        "name": "ФЛАНЕЦ ДИСКА С БОЛТАМИ 72-2308070 5 шпил. ОАО \"МТЗ\"",
        "article": "72-2308070"
    },
    {
        "code": "8402593",
        "name": "ФЛАНЕЦ ДИСКА С БОЛТАМИ 72-2308070-01 8 шпил. ОАО \"МТЗ\"",
        "article": "72-2308070-01"
    },
    {
        "code": "8402583",
        "name": "ФЛАНЕЦ СКОЛЬЗЯЩИЙ 72-2209014 (МТЗ-80/82) ОАО \"БЗТДиА\"",
        "article": "72-2209014"
    },
    {
        "code": "8406864",
        "name": "ЦАПФА 70-3001085-01 ПРАВАЯ (МТЗ-80) ОАО \"БЗТДиА\"",
        "article": "70-3001085-01"
    },
    {
        "code": "8411979",
        "name": "ЧАШКА ДИФФЕРЕНЦИАЛА 52-2303021 (МТЗ-82/1221/1523) ОАО \"МТЗ\"",
        "article": "52-2303021"
    },
    {
        "code": "8410999",
        "name": "ЧАШКА УПЛОТНИТЕЛЬНАЯ Ф80-3405108",
        "article": "Ф80-3405108"
    },
    {
        "code": "8525229",
        "name": "ЧЕКА ТЯГИ А61.05.100Р в СБ (РЗТ)",
        "article": "А61.05.100Р"
    },
    {
        "code": "8467050",
        "name": "ЧЕХОЛ 50-1702236 ООО \"ТрАз\"",
        "article": "50-1702236"
    },
    {
        "code": "8476378",
        "name": "ЧЕХОЛ 50-3502202 кожуха тормоза ООО \"ТрАз\"",
        "article": "50-3502202"
    },
    {
        "code": "8459876",
        "name": "ЧЕХОЛ 80-6702243-А РЫЧАГА КПП Н.О. ООО \"ТрАз\"",
        "article": "80-6702243-А"
    },
    {
        "code": "8488530",
        "name": "ЧЕХОЛ А13.36.001 (накладка педали подач. топлива) ОАО \"МТЗ\"",
        "article": "А13.36.001"
    },
    {
        "code": "8467661",
        "name": "ЧЕХОЛ нак. рулевого 50-3003019 (А35.32.005) ООО \"ТрАз\"",
        "article": "50-3003019"
    },
    {
        "code": "8544960",
        "name": "ШАЙБА 70-1721023 УПОРНАЯ ПОНИЖАЮЩЕГО РЕДУКТОРА",
        "article": "70-1721023"
    },
    {
        "code": "8425816",
        "name": "ШАЙБА 50-1701254-А (вал вторичный) ОАО \"МТЗ\"",
        "article": "50-1701254"
    },
    {
        "code": "8462611",
        "name": "ШАЙБА 50-4605068 Б1 Аналог 50-4605068",
        "article": "Б1"
    },
    {
        "code": "8422872",
        "name": "ШАЙБА 50-4605068-Б1 ОАО \"САЗ\" 50-4605068",
        "article": "Б1"
    },
    {
        "code": "8425817",
        "name": "ШАЙБА 70-1721318 маслоотражательная редуктора ОАО \"МТЗ\"",
        "article": "70-1721318"
    },
    {
        "code": "8443660",
        "name": "ШАЙБА 72-2308031",
        "article": "72-2308031"
    },
    {
        "code": "8517509",
        "name": "ШАЙБА 72-2308044 трубы шкворня",
        "article": "72-2308044"
    },
    {
        "code": "8437603",
        "name": "ШАЙБА 74-1701026",
        "article": "74-1701026"
    },
    {
        "code": "8513239",
        "name": "ШАЙБА 80-3001031 ОАО \"МТЗ\"",
        "article": "80-3001031"
    },
    {
        "code": "8422554",
        "name": "ШАЙБА БОЛТА МАХОВИКА 48-1002318",
        "article": "48-1002318"
    },
    {
        "code": "8403184",
        "name": "ШАЙБА ПРУЖИНЫ КЛАПАНА ВЕРХНЯЯ 240-1007055 ОАО \"ММЗ\"",
        "article": "240-1007055"
    },
    {
        "code": "8403180",
        "name": "ШАЙБА ПРУЖИНЫ КЛАПАНА НИЖНЯЯ 240-1007054 ОАО \"ММЗ\"",
        "article": "240-1007054"
    },
    {
        "code": "8461804",
        "name": "ШАЙБА РАСПОРНАЯ 70-1601083 ОАО \"МТЗ\"",
        "article": "70-1601083"
    },
    {
        "code": "8435995",
        "name": "ШАЙБА РАСПРЕДВАЛА 50-1006021-Б ОАО \"ММЗ\"",
        "article": "50-1006021Б"
    },
    {
        "code": "8435822",
        "name": "ШАЙБА СТОПОРНАЯ 85-1601086 (МТЗ-80/82/1221) ОАО \"БЗТДиА\"",
        "article": "85-1601086"
    },
    {
        "code": "8460010",
        "name": "ШАЙБА УПОРНАЯ 50-1602029",
        "article": "50-1602029"
    },
    {
        "code": "8403219",
        "name": "ШАЙБА УПОРНАЯ 72-2209016 (МТЗ) ОАО \"БЗТДиА\"",
        "article": "72-2209016"
    },
    {
        "code": "8441984",
        "name": "ШАЙБА УПОРНАЯ ШЕСТЕРНИ РАСПРЕД. ВАЛА 50-1006018 ОАО \"ММЗ\"",
        "article": "50-1006018"
    },
    {
        "code": "8436594",
        "name": "ШАРНИР 80-3003020-02 ПРАВЫЙ (УСИЛЕННЫЙ)",
        "article": "80-3003020-02"
    },
    {
        "code": "8436595",
        "name": "ШАРНИР 80-3003020-03 ЛЕВЫЙ (УСИЛЕННЫЙ)",
        "article": "80-3003020-03"
    },
    {
        "code": "8403254",
        "name": "ШАТУН Д-240 240-1004100-А (d 38) ОАО \"ММЗ\"",
        "article": "240-1004100-А"
    },
    {
        "code": "8452077",
        "name": "ШЕСТЕРНЯ 50-1701198-А Z=28 (МТЗ-80/82) ОАО \"МТЗ\"",
        "article": "50-1701198-А"
    },
    {
        "code": "8403474",
        "name": "ШЕСТЕРНЯ (МТЗ) 240-1005033 Z=38 привода масляного насоса ведущая ОАО \"ММЗ\"",
        "article": "240-1005033"
    },
    {
        "code": "8473118",
        "name": "ШЕСТЕРНЯ (МТЗ) 240-1005033-А Z=46 привода масляного насоса ведущая ОАО \"ММЗ\"",
        "article": "240-1005033"
    },
    {
        "code": "8416183",
        "name": "ШЕСТЕРНЯ (МТЗ) 240-1005033-А-01 Z=42 привода масляного насоса ведущая ОАО \"ММЗ\"",
        "article": "240-1005033-А-01"
    },
    {
        "code": "8386215",
        "name": "ШЕСТЕРНЯ (МТЗ) 240-1006214-А Z=40 РАСПРЕДВАЛА ОАО \"ММЗ\"",
        "article": "240-1006214-А"
    },
    {
        "code": "8461976",
        "name": "ШЕСТЕРНЯ (МТЗ) 240-1006240 ПРОМЕЖУТ (Z=53, угол накл. 28 град, до 27.01.2014 г) Аналог",
        "article": "240-1006240"
    },
    {
        "code": "8452075",
        "name": "ШЕСТЕРНЯ (МТЗ) 240-1006240-А2 (СТАР. ОБР. УГОЛ 28) ОАО \"ММЗ\"",
        "article": "240-1006240-А2"
    },
    {
        "code": "8462624",
        "name": "ШЕСТЕРНЯ (МТЗ) 240-1022061Б привода насоса НШ-10 Аналог",
        "article": "240-1022061Б"
    },
    {
        "code": "8462626",
        "name": "ШЕСТЕРНЯ (МТЗ) 50-1701045 СКОЛЬЗЯЩАЯ 3 ПЕРЕДАЧИ (вал перв. Z=21) Аналог",
        "article": "50-1701045"
    },
    {
        "code": "8403406",
        "name": "ШЕСТЕРНЯ (МТЗ) 50-1701045 СКОЛЬЗЯЩАЯ 3 ПЕРЕДАЧИ (вал перв. Z=21) ОАО \"МЗШ\"",
        "article": "50-1701045"
    },
    {
        "code": "8403407",
        "name": "ШЕСТЕРНЯ (МТЗ) 50-1701048-А СКОЛЬЗЯЩАЯ 4 И 5 ПЕРЕДАЧ Z=27/24 ОАО \"МЗШ\"",
        "article": "50-1701048"
    },
    {
        "code": "8403409",
        "name": "ШЕСТЕРНЯ (МТЗ) 50-1701196 ВЕДУЩАЯ 1 СТУПЕНИ РЕДУКТОРА Z=20/20 ОАО \"МЗШ\"",
        "article": "50-1701196"
    },
    {
        "code": "8403410",
        "name": "ШЕСТЕРНЯ (МТЗ) 50-1701198-А ВЕДУЩАЯ 2 СТУПЕНИ РЕДУКТОРА Z=28 ОАО \"МТЗ\"",
        "article": "50-1701198"
    },
    {
        "code": "8403412",
        "name": "ШЕСТЕРНЯ (МТЗ) 50-1701214 ВЕДОМАЯ 3 ПЕРЕДАЧИ Z=43 ОАО \"МЗШ\"",
        "article": "50-1701214"
    },
    {
        "code": "8403413",
        "name": "ШЕСТЕРНЯ (МТЗ) 50-1701216 ведомая 4-5 передачи (вал промеж) Z=40 ОАО \"МЗШ\"",
        "article": "50-1701216"
    },
    {
        "code": "8403414",
        "name": "ШЕСТЕРНЯ (МТЗ) 50-1701218 ведомая 5-ой пер.и з/х Z=38/19 ОАО \"МЗШ\"",
        "article": "50-1701218"
    },
    {
        "code": "8403477",
        "name": "ШЕСТЕРНЯ (МТЗ) 50-2403048 ПОЛУОСЕВАЯ Z=22 ОАО \"МЗШ\"",
        "article": "50-2403048"
    },
    {
        "code": "8403379",
        "name": "ШЕСТЕРНЯ (МТЗ) 52-1802061А ОАО \"МТЗ\"",
        "article": "52-1802061А"
    },
    {
        "code": "8403479",
        "name": "ШЕСТЕРНЯ (МТЗ) 52-1802091 ПРОМЕЖУТОЧНАЯ Z=22 ОАО \"МЗШ\"",
        "article": "52-1802091"
    },
    {
        "code": "8406613",
        "name": "ШЕСТЕРНЯ (МТЗ) 52-2302019 ВЕДОМАЯ",
        "article": "52-2302019"
    },
    {
        "code": "8462615",
        "name": "ШЕСТЕРНЯ (МТЗ) 52-2308061 ВЕДОМАЯ Z=12 Аналог",
        "article": "52-2308061"
    },
    {
        "code": "8403417",
        "name": "ШЕСТЕРНЯ (МТЗ) 70-1601088-Б ВЕДОМАЯ ПРИВОДА ВОМ Z=47 ОАО \"МЗШ\"",
        "article": "70-1601086Б"
    },
    {
        "code": "8403492",
        "name": "ШЕСТЕРНЯ (МТЗ) 70-1601331 ПРОМЕЖУТОЧНАЯ Z=27 ОАО \"МЗШ\"",
        "article": "70-1601331"
    },
    {
        "code": "8461981",
        "name": "ШЕСТЕРНЯ (МТЗ) 70-1701082 ПРОМЕЖУТОЧНАЯ ЗАДНЕГО ХОДА Z=31 Аналог",
        "article": "70-1701082"
    },
    {
        "code": "8462634",
        "name": "ШЕСТЕРНЯ (МТЗ) 70-1721025 понижающего редуктора НОВ.ОБР Z=34 Аналог",
        "article": "70-1721025"
    },
    {
        "code": "8403468",
        "name": "ШЕСТЕРНЯ (МТЗ) 70-1721041 ПРОМЕЖУТОЧНАЯ ПОНИЖАЮЩЕГО РЕДУКТОРА ОАО \"МЗШ\"",
        "article": "70-1721041"
    },
    {
        "code": "8461984",
        "name": "ШЕСТЕРНЯ (МТЗ) 70-2407053 ВАЛ (L=315 мм) Аналог",
        "article": "70-2407053"
    },
    {
        "code": "8403388",
        "name": "ШЕСТЕРНЯ (МТЗ) 70-2407053 ВАЛ (L=315 мм) ОАО \"МТЗ\"",
        "article": "70-2407053"
    },
    {
        "code": "8403387",
        "name": "ШЕСТЕРНЯ (МТЗ) 70-2407053-01 ВАЛ (КОРОТКАЯ ПРАВАЯ) (L=266 мм) ОАО \"МТЗ\"",
        "article": "70-2407053-01"
    },
    {
        "code": "8403420",
        "name": "ШЕСТЕРНЯ (МТЗ) 70-4202032 СОЛНЕЧНАЯ Z=30 ОАО \"МЗШ\"",
        "article": "70-4202032"
    },
    {
        "code": "8435786",
        "name": "ШЕСТЕРНЯ (МТЗ) 70-4202055 ОАО \"БЗТДиА\"",
        "article": "70-4202055"
    },
    {
        "code": "8462616",
        "name": "ШЕСТЕРНЯ (МТЗ) 72-2308062 ВЕДУЩАЯ Аналог",
        "article": "72-2308062"
    },
    {
        "code": "8422567",
        "name": "ШЕСТЕРНЯ (МТЗ) 80-4604032-А привода насоса НШ-32 Z=24 ОАО \"МЗШ\"",
        "article": "80-4604032А"
    },
    {
        "code": "8452076",
        "name": "ШЕСТЕРНЯ (МТЗ) Ф50-1701056-Б Z=26/43 ОАО \"МЗШ\"",
        "article": "Ф50-1701056Б"
    },
    {
        "code": "8406592",
        "name": "ШЕСТЕРНЯ (МТЗ) Ф50-1701224 1 передачи и заднего хода Z=32 ОАО \"МЗШ\"",
        "article": "Ф50-1701224"
    },
    {
        "code": "8406853",
        "name": "ШЕСТЕРНЯ 245-1006311-В1 привода топливного насоса Z=30/40 ОАО \"ММЗ\"",
        "article": "245-1006311-В1"
    },
    {
        "code": "8403214",
        "name": "ШЕСТЕРНЯ 50-1601024 ОАО \"МЗШ\"",
        "article": "50-1601024"
    },
    {
        "code": "8435791",
        "name": "ШЕСТЕРНЯ 50-1601088-Б ОАО \"МЗШ\"",
        "article": "50-1601088Б"
    },
    {
        "code": "8435784",
        "name": "ШЕСТЕРНЯ 50-1601331-А ПРОМЕЖУТОЧНАЯ ОАО \"МЗШ\"",
        "article": "50-1601331-А"
    },
    {
        "code": "8421246",
        "name": "ШЕСТЕРНЯ 50-1721025 Z=30 ОАО \"МЗШ\"",
        "article": "50-1721025"
    },
    {
        "code": "8435775",
        "name": "ШЕСТЕРНЯ 50-4604032-А1 ОАО \"МЗШ\"",
        "article": "50-4604032-А1"
    },
    {
        "code": "8438163",
        "name": "ШЕСТЕРНЯ 70-4202025 ОАО \"БЗТДиА\"",
        "article": "70-4202025"
    },
    {
        "code": "8403444",
        "name": "ШЕСТЕРНЯ 70-4202043 КОРОННАЯ ОАО \"БЗТДиА\"",
        "article": "70-4202043"
    },
    {
        "code": "8398176",
        "name": "ШЕСТЕРНЯ 74-1721080сб Z=34 ОАО \"МЗШ\"",
        "article": "74-1721080"
    },
    {
        "code": "8542081",
        "name": "ШЕСТЕРНЯ ВЕДУЩАЯ 70-1701196 ТАРА",
        "article": "70-1701196"
    },
    {
        "code": "8522840",
        "name": "ШЕСТЕРНЯ РАСПРЕДЕЛЕНИЯ КОЛЕНЧАТОГО ВАЛА 240-1005030-Д (МТЗ) (ОАО ММЗ) старого обр. угол 28 град",
        "article": "240-1005030-Д"
    },
    {
        "code": "8414015",
        "name": "ШКВОРЕНЬ 50-4605079-Б ОАО \"ВЗТЗЧ\"",
        "article": "50-4605079-Б"
    },
    {
        "code": "8425868",
        "name": "ШКИВ ВОДЯНОГО НАСОСА 240-1307061-02 (МТЗ)",
        "article": "240-1307061-02"
    },
    {
        "code": "8524856",
        "name": "ШКИВ КОЛЕНВАЛА 240-1005131 Б-02 (МТЗ-80) (1-но руч.) Аналог 240-1005131",
        "article": "Б-02"
    },
    {
        "code": "8463548",
        "name": "ШКИВ КОЛЕНВАЛА 240-1005131 М (2-х руч) ОАО \"ММЗ\" 240-1005131",
        "article": "М"
    },
    {
        "code": "8461030",
        "name": "ШКИВ КОЛЕНВАЛА 240-1005131-Г ОАО \"ММЗ\"",
        "article": "240-1005131-Г"
    },
    {
        "code": "8397856",
        "name": "ШЛАНГ К КОРПУСУ ТЕРМОСТАТА 50-1306028-Б2 ООО \"ТрАз\"",
        "article": "50-1306028-Б2"
    },
    {
        "code": "8462637",
        "name": "ШЛАНГ МАНОМЕТРА 70-3801180 Аналог",
        "article": "70-3801180"
    },
    {
        "code": "8460297",
        "name": "ШНУР 70-1310121",
        "article": "70-1310121"
    },
    {
        "code": "8482671",
        "name": "ШПЛИНТ ПРУЖИННЫЙ А.61.07.001",
        "article": "Аналог"
    },
    {
        "code": "8431922",
        "name": "ШПЛИНТ ПРУЖИННЫЙ А.61.07.001 ОАО",
        "article": "\"МТЗ\""
    },
    {
        "code": "8406598",
        "name": "ШПОНКА 50-3104016 (ПОЛУОСЬ МТЗ) ОАО",
        "article": "\"МТЗ\""
    },
    {
        "code": "8443743",
        "name": "ШПОНКА ВАЛА КОЛН. 245-1005013 6Х9Х22 ОАО",
        "article": "\"ММЗ\""
    },
    {
        "code": "8404233",
        "name": "ШТИФТ",
        "article": "10*40"
    },
    {
        "code": "8454686",
        "name": "ШТИФТ 50-4605027 ОАО",
        "article": "\"БЗТДиА\""
    },
    {
        "code": "8462317",
        "name": "ШТИФТ",
        "article": "52-2308094"
    },
    {
        "code": "8424809",
        "name": "ШТИФТ 70-1601114 (сухарь вилки 80-1601191) (МТЗ-1221) ОАО",
        "article": "\"САЗ\""
    },
    {
        "code": "8443337",
        "name": "ШТИФТ ПРУЖИННЫЙ 917340 А.8Х45. 65Г. ГОСТ",
        "article": "14229-93"
    },
    {
        "code": "8435365",
        "name": "ШТИФТ САТЕЛЛИТА 70-4202431 (ШТИФТ DIN 1481 М4Х30) ОАО",
        "article": "\"БЗТДиА\""
    },
    {
        "code": "8452815",
        "name": "ШТИФТ УСТАНОВОЧНЫЙ Д01-015 (D=14,3 мм, L=31 мм) ОАО",
        "article": "\"САЗ\""
    },
    {
        "code": "8482153",
        "name": "ШТИФТ ШЦК 8х25 ОАО",
        "article": "\"МТЗ\""
    },
    {
        "code": "8476379",
        "name": "ШТУЦЕР 240-3509232 ОАО",
        "article": "\"ММЗ\""
    },
    {
        "code": "8411994",
        "name": "ШТУЦЕР ВВЕРТНЫЙ 70-3506022 ОАО",
        "article": "\"САЗ\""
    },
    {
        "code": "8442003",
        "name": "ШТУЦЕР КОРПУСА ТЕРМОСТАТА 245-1306027 ОАО",
        "article": "\"ММЗ\""
    },
    {
        "code": "8404292",
        "name": "ШТУЦЕР ТОПЛИВНЫЙ 240-1111112 (10 мм)",
        "article": "(МТЗ-80/82)"
    },
    {
        "code": "8484344",
        "name": "ШТУЦЕР ТОПЛИВНЫЙ 240-1111112-Б (8 мм)",
        "article": "(МТЗ-80/82)"
    },
    {
        "code": "8404255",
        "name": "ШТУЦЕР ТОПЛИВНЫЙ",
        "article": "УТН3-1111485"
    }
]
